[{"id":"008aff11-cf5c-4b7f-b204-858709779b26","broadcaster_code":"SEVEN","channel_id":"RACING.COM","channel_name":"RACING.COM","duration":"00:30","dvb_triplet":"1013:0502:0528","end":"2020-05-26T11:00:00+00:00","lcn":78,"start":"2020-05-26T10:30:00+00:00","tags":["captioned"],"updated_at":"2020-05-21T07:32:05+00:00","title":"Tuesdays With Terry"},{"id":"8beafae7-da93-4125-9d93-8559f612f85f","broadcaster_code":"SEVEN","channel_id":"RACING.COM","channel_name":"RACING.COM","duration":"01:00","dvb_triplet":"1013:0502:0528","end":"2020-05-26T12:00:00+00:00","lcn":78,"episode_id":"c6b9fc0c-898c-4352-a5e7-15cff499cc10","start":"2020-05-26T11:00:00+00:00","tags":["captioned"],"updated_at":"2020-05-17T21:37:03+00:00","title":"Sectional Stars","related":{"episodes":[{"id":"c6b9fc0c-898c-4352-a5e7-15cff499cc10","updated_at":"2020-05-17T21:37:03+00:00","draft":false,"on_air":true,"synopsis":"Brent Zerafa and Nic Ashman delve deep into races and find Sectional Stars from the feature meetings. Hidden gems with horses running on and the good oil on future favourites - everything to put into your black book. (2016)","title":"Sectional Stars","categories":["channel_id/RACING.COM","genres/Sport","subgenres/Horse Racing","classification/NC","content_type/series"],"related":{"images":[{"id":"4c0a7d70-4979-4821-8c85-35e38e23862c","url":"http://img-store-prod.switch.tv/images/4c0a7d70-4979-4821-8c85-35e38e23862c/481495_racing.com_red_logo_16x9_rgb.png"}]},"episode_id":"/20SEC38A","broadcaster":"SEVEN"}]}},{"id":"80dd7a36-9dc7-49bf-8313-917f1248a86d","broadcaster_code":"SEVEN","channel_id":"RACING.COM","channel_name":"RACING.COM","duration":"00:30","dvb_triplet":"1013:0502:0528","end":"2020-05-26T12:30:00+00:00","lcn":78,"episode_id":"b0de084d-aa99-4861-8d96-5850a6896fb1","start":"2020-05-26T12:00:00+00:00","tags":["captioned"],"updated_at":"2020-05-17T21:41:06+00:00","title":"The Wrap - Group 1 Glory","related":{"episodes":[{"id":"b0de084d-aa99-4861-8d96-5850a6896fb1","updated_at":"2020-05-17T21:38:41+00:00","draft":false,"on_air":true,"synopsis":"Might and Power. Terry Bailey and Greg Miles have called some of the greatest champions of the Australian Turf. In Group One Glory, they remember all their favourite horses and their stories. (2016)","title":"The Wrap - Group 1 Glory","categories":["channel_id/RACING.COM","genres/Sport","subgenres/Horse Racing","classification/NC","content_type/series"],"related":{"images":[{"id":"e550c67b-a668-45f5-a6f5-674f4b19f99b","url":"http://img-store-prod.switch.tv/images/e550c67b-a668-45f5-a6f5-674f4b19f99b/481495_racing.com_red_logo_16x9_rgb.png"}]},"episode_id":"/19G1G12A","broadcaster":"SEVEN"}]}},{"id":"463788b8-6509-4991-ba0d-cd8cb778f2f6","broadcaster_code":"SEVEN","channel_id":"RACING.COM","channel_name":"RACING.COM","duration":"00:30","dvb_triplet":"1013:0502:0528","end":"2020-05-26T13:00:00+00:00","lcn":78,"start":"2020-05-26T12:30:00+00:00","tags":["captioned"],"updated_at":"2020-05-17T21:39:12+00:00","title":"Raceday Review - Hamilton"},{"id":"ae47928e-7af2-4d28-8dfd-86ef78774da9","broadcaster_code":"SEVEN","channel_id":"RACING.COM","channel_name":"RACING.COM","duration":"01:00","dvb_triplet":"1013:0502:0528","end":"2020-05-26T14:00:00+00:00","lcn":78,"episode_id":"c6b9fc0c-898c-4352-a5e7-15cff499cc10","start":"2020-05-26T13:00:00+00:00","tags":["captioned"],"updated_at":"2020-05-17T21:40:26+00:00","title":"Sectional Stars","related":{"episodes":[{"id":"c6b9fc0c-898c-4352-a5e7-15cff499cc10","updated_at":"2020-05-17T21:37:03+00:00","draft":false,"on_air":true,"synopsis":"Brent Zerafa and Nic Ashman delve deep into races and find Sectional Stars from the feature meetings. Hidden gems with horses running on and the good oil on future favourites - everything to put into your black book. (2016)","title":"Sectional Stars","categories":["channel_id/RACING.COM","genres/Sport","subgenres/Horse Racing","classification/NC","content_type/series"],"related":{"images":[{"id":"4c0a7d70-4979-4821-8c85-35e38e23862c","url":"http://img-store-prod.switch.tv/images/4c0a7d70-4979-4821-8c85-35e38e23862c/481495_racing.com_red_logo_16x9_rgb.png"}]},"episode_id":"/20SEC38A","broadcaster":"SEVEN"}]}},{"id":"14f8ffa3-7e87-4c59-88d3-ecbde1ed4a63","broadcaster_code":"SEVEN","channel_id":"RACING.COM","channel_name":"RACING.COM","duration":"00:30","dvb_triplet":"1013:0502:0528","end":"2020-05-26T14:30:00+00:00","lcn":78,"episode_id":"37443351-3d49-4952-aa90-91ad40b45434","start":"2020-05-26T14:00:00+00:00","tags":["captioned"],"updated_at":"2020-05-18T21:39:34+00:00","title":"Raceday Review - Hamilton","related":{"episodes":[{"id":"37443351-3d49-4952-aa90-91ad40b45434","updated_at":"2020-05-17T21:41:08+00:00","draft":false,"on_air":true,"synopsis":"A full recap of racing from Hamilton - Tuesday 26th May 2020. (2016)","title":"Raceday Review - Hamilton","categories":["channel_id/RACING.COM","genres/Sport","subgenres/Horse Racing","classification/NC","content_type/series"],"related":{"images":[{"id":"441dc398-64ad-471b-af7d-2ddbc399256e","url":"http://img-store-prod.switch.tv/images/441dc398-64ad-471b-af7d-2ddbc399256e/481495_racing.com_red_logo_16x9_rgb.png"}]},"episode_id":"/RV26051A","broadcaster":"SEVEN"}]}},{"id":"150ce6dc-4249-49e9-b3e3-ad7bbab75c1f","broadcaster_code":"SEVEN","channel_id":"RACING.COM","channel_name":"RACING.COM","duration":"00:30","dvb_triplet":"1013:0502:0528","end":"2020-05-26T15:00:00+00:00","lcn":78,"episode_id":"1ca35eb2-facb-4153-aa54-427aca49de55","start":"2020-05-26T14:30:00+00:00","tags":["captioned"],"updated_at":"2020-05-18T21:38:47+00:00","title":"Raceday Review - Echuca","related":{"episodes":[{"id":"1ca35eb2-facb-4153-aa54-427aca49de55","updated_at":"2020-05-16T21:38:18+00:00","draft":false,"on_air":true,"synopsis":"A full recap of racing from Echuca - Monday 25th May 2020. (2016)","title":"Raceday Review - Echuca","categories":["channel_id/RACING.COM","genres/Sport","subgenres/Horse Racing","classification/NC","content_type/series"],"related":{"images":[{"id":"9c82404c-15f9-43fb-a9e1-0019d04433e1","url":"http://img-store-prod.switch.tv/images/9c82404c-15f9-43fb-a9e1-0019d04433e1/481495_racing.com_red_logo_16x9_rgb.png"}]},"episode_id":"/RV25051A","broadcaster":"SEVEN"}]}},{"id":"6cf99bf6-869a-42e8-9d17-4e9bade84483","broadcaster_code":"SEVEN","channel_id":"RACING.COM","channel_name":"RACING.COM","duration":"01:00","dvb_triplet":"1013:0502:0528","end":"2020-05-26T16:00:00+00:00","lcn":78,"episode_id":"c6b9fc0c-898c-4352-a5e7-15cff499cc10","start":"2020-05-26T15:00:00+00:00","tags":["captioned"],"updated_at":"2020-05-18T21:39:40+00:00","title":"Sectional Stars","related":{"episodes":[{"id":"c6b9fc0c-898c-4352-a5e7-15cff499cc10","updated_at":"2020-05-17T21:37:03+00:00","draft":false,"on_air":true,"synopsis":"Brent Zerafa and Nic Ashman delve deep into races and find Sectional Stars from the feature meetings. Hidden gems with horses running on and the good oil on future favourites - everything to put into your black book. (2016)","title":"Sectional Stars","categories":["channel_id/RACING.COM","genres/Sport","subgenres/Horse Racing","classification/NC","content_type/series"],"related":{"images":[{"id":"4c0a7d70-4979-4821-8c85-35e38e23862c","url":"http://img-store-prod.switch.tv/images/4c0a7d70-4979-4821-8c85-35e38e23862c/481495_racing.com_red_logo_16x9_rgb.png"}]},"episode_id":"/20SEC38A","broadcaster":"SEVEN"}]}},{"id":"4007b9ee-fa02-4624-a83a-fa3643235144","broadcaster_code":"SEVEN","channel_id":"RACING.COM","channel_name":"RACING.COM","duration":"00:30","dvb_triplet":"1013:0502:0528","end":"2020-05-26T16:30:00+00:00","lcn":78,"episode_id":"37443351-3d49-4952-aa90-91ad40b45434","start":"2020-05-26T16:00:00+00:00","tags":["captioned"],"updated_at":"2020-05-18T21:38:37+00:00","title":"Raceday Review - Hamilton","related":{"episodes":[{"id":"37443351-3d49-4952-aa90-91ad40b45434","updated_at":"2020-05-17T21:41:08+00:00","draft":false,"on_air":true,"synopsis":"A full recap of racing from Hamilton - Tuesday 26th May 2020. (2016)","title":"Raceday Review - Hamilton","categories":["channel_id/RACING.COM","genres/Sport","subgenres/Horse Racing","classification/NC","content_type/series"],"related":{"images":[{"id":"441dc398-64ad-471b-af7d-2ddbc399256e","url":"http://img-store-prod.switch.tv/images/441dc398-64ad-471b-af7d-2ddbc399256e/481495_racing.com_red_logo_16x9_rgb.png"}]},"episode_id":"/RV26051A","broadcaster":"SEVEN"}]}},{"id":"9f30f37e-7183-4e29-84ce-50a082279960","broadcaster_code":"SEVEN","channel_id":"RACING.COM","channel_name":"RACING.COM","duration":"00:30","dvb_triplet":"1013:0502:0528","end":"2020-05-26T17:00:00+00:00","lcn":78,"episode_id":"1ca35eb2-facb-4153-aa54-427aca49de55","start":"2020-05-26T16:30:00+00:00","tags":["captioned"],"updated_at":"2020-05-18T21:37:48+00:00","title":"Raceday Review - Echuca","related":{"episodes":[{"id":"1ca35eb2-facb-4153-aa54-427aca49de55","updated_at":"2020-05-16T21:38:18+00:00","draft":false,"on_air":true,"synopsis":"A full recap of racing from Echuca - Monday 25th May 2020. (2016)","title":"Raceday Review - Echuca","categories":["channel_id/RACING.COM","genres/Sport","subgenres/Horse Racing","classification/NC","content_type/series"],"related":{"images":[{"id":"9c82404c-15f9-43fb-a9e1-0019d04433e1","url":"http://img-store-prod.switch.tv/images/9c82404c-15f9-43fb-a9e1-0019d04433e1/481495_racing.com_red_logo_16x9_rgb.png"}]},"episode_id":"/RV25051A","broadcaster":"SEVEN"}]}},{"id":"dea6779c-7ace-49fd-a387-a5ff697c7723","broadcaster_code":"SEVEN","channel_id":"RACING.COM","channel_name":"RACING.COM","duration":"00:30","dvb_triplet":"1013:0502:0528","end":"2020-05-26T17:30:00+00:00","lcn":78,"episode_id":"37443351-3d49-4952-aa90-91ad40b45434","start":"2020-05-26T17:00:00+00:00","tags":["captioned"],"updated_at":"2020-05-18T21:37:14+00:00","title":"Raceday Review - Hamilton","related":{"episodes":[{"id":"37443351-3d49-4952-aa90-91ad40b45434","updated_at":"2020-05-17T21:41:08+00:00","draft":false,"on_air":true,"synopsis":"A full recap of racing from Hamilton - Tuesday 26th May 2020. (2016)","title":"Raceday Review - Hamilton","categories":["channel_id/RACING.COM","genres/Sport","subgenres/Horse Racing","classification/NC","content_type/series"],"related":{"images":[{"id":"441dc398-64ad-471b-af7d-2ddbc399256e","url":"http://img-store-prod.switch.tv/images/441dc398-64ad-471b-af7d-2ddbc399256e/481495_racing.com_red_logo_16x9_rgb.png"}]},"episode_id":"/RV26051A","broadcaster":"SEVEN"}]}},{"id":"e66d3a85-3a1f-4aba-a1d7-5ea7000a9155","broadcaster_code":"SEVEN","channel_id":"RACING.COM","channel_name":"RACING.COM","duration":"00:30","dvb_triplet":"1013:0502:0528","end":"2020-05-26T18:00:00+00:00","lcn":78,"episode_id":"1ca35eb2-facb-4153-aa54-427aca49de55","start":"2020-05-26T17:30:00+00:00","tags":["captioned"],"updated_at":"2020-05-18T21:37:57+00:00","title":"Raceday Review - Echuca","related":{"episodes":[{"id":"1ca35eb2-facb-4153-aa54-427aca49de55","updated_at":"2020-05-16T21:38:18+00:00","draft":false,"on_air":true,"synopsis":"A full recap of racing from Echuca - Monday 25th May 2020. (2016)","title":"Raceday Review - Echuca","categories":["channel_id/RACING.COM","genres/Sport","subgenres/Horse Racing","classification/NC","content_type/series"],"related":{"images":[{"id":"9c82404c-15f9-43fb-a9e1-0019d04433e1","url":"http://img-store-prod.switch.tv/images/9c82404c-15f9-43fb-a9e1-0019d04433e1/481495_racing.com_red_logo_16x9_rgb.png"}]},"episode_id":"/RV25051A","broadcaster":"SEVEN"}]}},{"id":"70f6b487-db11-4a33-8d61-c1b8b05ad602","broadcaster_code":"SEVEN","channel_id":"RACING.COM","channel_name":"RACING.COM","duration":"00:30","dvb_triplet":"1013:0502:0528","end":"2020-05-26T18:30:00+00:00","lcn":78,"episode_id":"37443351-3d49-4952-aa90-91ad40b45434","start":"2020-05-26T18:00:00+00:00","tags":["captioned"],"updated_at":"2020-05-18T21:38:12+00:00","title":"Raceday Review - Hamilton","related":{"episodes":[{"id":"37443351-3d49-4952-aa90-91ad40b45434","updated_at":"2020-05-17T21:41:08+00:00","draft":false,"on_air":true,"synopsis":"A full recap of racing from Hamilton - Tuesday 26th May 2020. (2016)","title":"Raceday Review - Hamilton","categories":["channel_id/RACING.COM","genres/Sport","subgenres/Horse Racing","classification/NC","content_type/series"],"related":{"images":[{"id":"441dc398-64ad-471b-af7d-2ddbc399256e","url":"http://img-store-prod.switch.tv/images/441dc398-64ad-471b-af7d-2ddbc399256e/481495_racing.com_red_logo_16x9_rgb.png"}]},"episode_id":"/RV26051A","broadcaster":"SEVEN"}]}},{"id":"5db4bbd5-eb8c-4b79-9af1-548a05c5a01d","broadcaster_code":"SEVEN","channel_id":"RACING.COM","channel_name":"RACING.COM","duration":"00:30","dvb_triplet":"1013:0502:0528","end":"2020-05-26T19:00:00+00:00","lcn":78,"episode_id":"1ca35eb2-facb-4153-aa54-427aca49de55","start":"2020-05-26T18:30:00+00:00","tags":["captioned"],"updated_at":"2020-05-18T21:39:42+00:00","title":"Raceday Review - Echuca","related":{"episodes":[{"id":"1ca35eb2-facb-4153-aa54-427aca49de55","updated_at":"2020-05-16T21:38:18+00:00","draft":false,"on_air":true,"synopsis":"A full recap of racing from Echuca - Monday 25th May 2020. (2016)","title":"Raceday Review - Echuca","categories":["channel_id/RACING.COM","genres/Sport","subgenres/Horse Racing","classification/NC","content_type/series"],"related":{"images":[{"id":"9c82404c-15f9-43fb-a9e1-0019d04433e1","url":"http://img-store-prod.switch.tv/images/9c82404c-15f9-43fb-a9e1-0019d04433e1/481495_racing.com_red_logo_16x9_rgb.png"}]},"episode_id":"/RV25051A","broadcaster":"SEVEN"}]}},{"id":"98c622c5-78ce-4e34-8c9d-b246d092345c","broadcaster_code":"SEVEN","channel_id":"RACING.COM","channel_name":"RACING.COM","duration":"01:00","dvb_triplet":"1013:0502:0528","end":"2020-05-26T20:00:00+00:00","lcn":78,"episode_id":"c6b9fc0c-898c-4352-a5e7-15cff499cc10","start":"2020-05-26T19:00:00+00:00","tags":["captioned"],"updated_at":"2020-05-21T07:32:48+00:00","title":"Sectional Stars","related":{"episodes":[{"id":"c6b9fc0c-898c-4352-a5e7-15cff499cc10","updated_at":"2020-05-17T21:37:03+00:00","draft":false,"on_air":true,"synopsis":"Brent Zerafa and Nic Ashman delve deep into races and find Sectional Stars from the feature meetings. Hidden gems with horses running on and the good oil on future favourites - everything to put into your black book. (2016)","title":"Sectional Stars","categories":["channel_id/RACING.COM","genres/Sport","subgenres/Horse Racing","classification/NC","content_type/series"],"related":{"images":[{"id":"4c0a7d70-4979-4821-8c85-35e38e23862c","url":"http://img-store-prod.switch.tv/images/4c0a7d70-4979-4821-8c85-35e38e23862c/481495_racing.com_red_logo_16x9_rgb.png"}]},"episode_id":"/20SEC38A","broadcaster":"SEVEN"}]}},{"id":"0c099315-2e8e-45d9-847b-f60c8253fb3c","broadcaster_code":"SEVEN","channel_id":"RACING.COM","channel_name":"RACING.COM","duration":"00:30","dvb_triplet":"1013:0502:0528","end":"2020-05-26T20:30:00+00:00","lcn":78,"episode_id":"1ca35eb2-facb-4153-aa54-427aca49de55","start":"2020-05-26T20:00:00+00:00","tags":["captioned"],"updated_at":"2020-05-18T21:37:20+00:00","title":"Raceday Review - Echuca","related":{"episodes":[{"id":"1ca35eb2-facb-4153-aa54-427aca49de55","updated_at":"2020-05-16T21:38:18+00:00","draft":false,"on_air":true,"synopsis":"A full recap of racing from Echuca - Monday 25th May 2020. (2016)","title":"Raceday Review - Echuca","categories":["channel_id/RACING.COM","genres/Sport","subgenres/Horse Racing","classification/NC","content_type/series"],"related":{"images":[{"id":"9c82404c-15f9-43fb-a9e1-0019d04433e1","url":"http://img-store-prod.switch.tv/images/9c82404c-15f9-43fb-a9e1-0019d04433e1/481495_racing.com_red_logo_16x9_rgb.png"}]},"episode_id":"/RV25051A","broadcaster":"SEVEN"}]}},{"id":"5b71bb9c-2f00-4e70-bfb4-90b4c0f89807","broadcaster_code":"SEVEN","channel_id":"RACING.COM","channel_name":"RACING.COM","duration":"00:30","dvb_triplet":"1013:0502:0528","end":"2020-05-26T21:00:00+00:00","lcn":78,"episode_id":"37443351-3d49-4952-aa90-91ad40b45434","start":"2020-05-26T20:30:00+00:00","tags":["captioned"],"updated_at":"2020-05-18T21:38:07+00:00","title":"Raceday Review - Hamilton","related":{"episodes":[{"id":"37443351-3d49-4952-aa90-91ad40b45434","updated_at":"2020-05-17T21:41:08+00:00","draft":false,"on_air":true,"synopsis":"A full recap of racing from Hamilton - Tuesday 26th May 2020. (2016)","title":"Raceday Review - Hamilton","categories":["channel_id/RACING.COM","genres/Sport","subgenres/Horse Racing","classification/NC","content_type/series"],"related":{"images":[{"id":"441dc398-64ad-471b-af7d-2ddbc399256e","url":"http://img-store-prod.switch.tv/images/441dc398-64ad-471b-af7d-2ddbc399256e/481495_racing.com_red_logo_16x9_rgb.png"}]},"episode_id":"/RV26051A","broadcaster":"SEVEN"}]}},{"id":"4090052a-6bc2-4fc1-826b-0007b44754d0","broadcaster_code":"SEVEN","channel_id":"RACING.COM","channel_name":"RACING.COM","duration":"00:30","dvb_triplet":"1013:0502:0528","end":"2020-05-26T21:30:00+00:00","lcn":78,"episode_id":"1ca35eb2-facb-4153-aa54-427aca49de55","start":"2020-05-26T21:00:00+00:00","tags":["captioned"],"updated_at":"2020-05-18T21:38:33+00:00","title":"Raceday Review - Echuca","related":{"episodes":[{"id":"1ca35eb2-facb-4153-aa54-427aca49de55","updated_at":"2020-05-16T21:38:18+00:00","draft":false,"on_air":true,"synopsis":"A full recap of racing from Echuca - Monday 25th May 2020. (2016)","title":"Raceday Review - Echuca","categories":["channel_id/RACING.COM","genres/Sport","subgenres/Horse Racing","classification/NC","content_type/series"],"related":{"images":[{"id":"9c82404c-15f9-43fb-a9e1-0019d04433e1","url":"http://img-store-prod.switch.tv/images/9c82404c-15f9-43fb-a9e1-0019d04433e1/481495_racing.com_red_logo_16x9_rgb.png"}]},"episode_id":"/RV25051A","broadcaster":"SEVEN"}]}},{"id":"7ee0ca9b-32d6-45ba-89db-295401cb4065","broadcaster_code":"SEVEN","channel_id":"RACING.COM","channel_name":"RACING.COM","duration":"00:30","dvb_triplet":"1013:0502:0528","end":"2020-05-26T22:00:00+00:00","lcn":78,"episode_id":"37443351-3d49-4952-aa90-91ad40b45434","start":"2020-05-26T21:30:00+00:00","tags":["captioned"],"updated_at":"2020-05-18T21:39:34+00:00","title":"Raceday Review - Hamilton","related":{"episodes":[{"id":"37443351-3d49-4952-aa90-91ad40b45434","updated_at":"2020-05-17T21:41:08+00:00","draft":false,"on_air":true,"synopsis":"A full recap of racing from Hamilton - Tuesday 26th May 2020. (2016)","title":"Raceday Review - Hamilton","categories":["channel_id/RACING.COM","genres/Sport","subgenres/Horse Racing","classification/NC","content_type/series"],"related":{"images":[{"id":"441dc398-64ad-471b-af7d-2ddbc399256e","url":"http://img-store-prod.switch.tv/images/441dc398-64ad-471b-af7d-2ddbc399256e/481495_racing.com_red_logo_16x9_rgb.png"}]},"episode_id":"/RV26051A","broadcaster":"SEVEN"}]}},{"id":"8d8d10e4-0523-4e2c-9033-566f7b822576","broadcaster_code":"SEVEN","channel_id":"RACING.COM","channel_name":"RACING.COM","duration":"00:30","dvb_triplet":"1013:0502:0528","end":"2020-05-26T22:30:00+00:00","lcn":78,"episode_id":"1ca35eb2-facb-4153-aa54-427aca49de55","start":"2020-05-26T22:00:00+00:00","tags":["captioned"],"updated_at":"2020-05-18T21:38:20+00:00","title":"Raceday Review - Echuca","related":{"episodes":[{"id":"1ca35eb2-facb-4153-aa54-427aca49de55","updated_at":"2020-05-16T21:38:18+00:00","draft":false,"on_air":true,"synopsis":"A full recap of racing from Echuca - Monday 25th May 2020. (2016)","title":"Raceday Review - Echuca","categories":["channel_id/RACING.COM","genres/Sport","subgenres/Horse Racing","classification/NC","content_type/series"],"related":{"images":[{"id":"9c82404c-15f9-43fb-a9e1-0019d04433e1","url":"http://img-store-prod.switch.tv/images/9c82404c-15f9-43fb-a9e1-0019d04433e1/481495_racing.com_red_logo_16x9_rgb.png"}]},"episode_id":"/RV25051A","broadcaster":"SEVEN"}]}},{"id":"b70a3728-f848-4834-8a88-f12d732aaa30","broadcaster_code":"SEVEN","channel_id":"RACING.COM","channel_name":"RACING.COM","duration":"01:00","dvb_triplet":"1013:0502:0528","end":"2020-05-26T23:30:00+00:00","lcn":78,"episode_id":"c6b9fc0c-898c-4352-a5e7-15cff499cc10","start":"2020-05-26T22:30:00+00:00","tags":["captioned"],"updated_at":"2020-05-18T21:38:23+00:00","title":"Sectional Stars","related":{"episodes":[{"id":"c6b9fc0c-898c-4352-a5e7-15cff499cc10","updated_at":"2020-05-17T21:37:03+00:00","draft":false,"on_air":true,"synopsis":"Brent Zerafa and Nic Ashman delve deep into races and find Sectional Stars from the feature meetings. Hidden gems with horses running on and the good oil on future favourites - everything to put into your black book. (2016)","title":"Sectional Stars","categories":["channel_id/RACING.COM","genres/Sport","subgenres/Horse Racing","classification/NC","content_type/series"],"related":{"images":[{"id":"4c0a7d70-4979-4821-8c85-35e38e23862c","url":"http://img-store-prod.switch.tv/images/4c0a7d70-4979-4821-8c85-35e38e23862c/481495_racing.com_red_logo_16x9_rgb.png"}]},"episode_id":"/20SEC38A","broadcaster":"SEVEN"}]}},{"id":"10c402fb-6051-4227-af6f-8d45c3818f9b","broadcaster_code":"SEVEN","channel_id":"RACING.COM","channel_name":"RACING.COM","duration":"00:30","dvb_triplet":"1013:0502:0528","end":"2020-05-27T00:00:00+00:00","lcn":78,"episode_id":"b0de084d-aa99-4861-8d96-5850a6896fb1","start":"2020-05-26T23:30:00+00:00","tags":["captioned"],"updated_at":"2020-05-18T21:38:25+00:00","title":"The Wrap - Group 1 Glory","related":{"episodes":[{"id":"b0de084d-aa99-4861-8d96-5850a6896fb1","updated_at":"2020-05-17T21:38:41+00:00","draft":false,"on_air":true,"synopsis":"Might and Power. Terry Bailey and Greg Miles have called some of the greatest champions of the Australian Turf. In Group One Glory, they remember all their favourite horses and their stories. (2016)","title":"The Wrap - Group 1 Glory","categories":["channel_id/RACING.COM","genres/Sport","subgenres/Horse Racing","classification/NC","content_type/series"],"related":{"images":[{"id":"e550c67b-a668-45f5-a6f5-674f4b19f99b","url":"http://img-store-prod.switch.tv/images/e550c67b-a668-45f5-a6f5-674f4b19f99b/481495_racing.com_red_logo_16x9_rgb.png"}]},"episode_id":"/19G1G12A","broadcaster":"SEVEN"}]}},{"id":"13bcd597-8548-47fd-95c3-cca3a4e4bca2","broadcaster_code":"SEVEN","channel_id":"RACING.COM","channel_name":"RACING.COM","duration":"01:00","dvb_triplet":"1013:0502:0528","end":"2020-05-27T01:00:00+00:00","lcn":78,"start":"2020-05-27T00:00:00+00:00","tags":["captioned"],"updated_at":"2020-05-26T07:27:56+00:00","title":"Australasian Racing Year"},{"id":"58b1a532-1cef-437a-ac2a-59e70f0ca539","broadcaster_code":"SEVEN","channel_id":"RACING.COM","channel_name":"RACING.COM","duration":"01:00","dvb_triplet":"1013:0502:0528","end":"2020-05-27T02:00:00+00:00","lcn":78,"episode_id":"c6b9fc0c-898c-4352-a5e7-15cff499cc10","start":"2020-05-27T01:00:00+00:00","tags":["captioned"],"updated_at":"2020-05-18T21:39:23+00:00","title":"Sectional Stars","related":{"episodes":[{"id":"c6b9fc0c-898c-4352-a5e7-15cff499cc10","updated_at":"2020-05-17T21:37:03+00:00","draft":false,"on_air":true,"synopsis":"Brent Zerafa and Nic Ashman delve deep into races and find Sectional Stars from the feature meetings. Hidden gems with horses running on and the good oil on future favourites - everything to put into your black book. (2016)","title":"Sectional Stars","categories":["channel_id/RACING.COM","genres/Sport","subgenres/Horse Racing","classification/NC","content_type/series"],"related":{"images":[{"id":"4c0a7d70-4979-4821-8c85-35e38e23862c","url":"http://img-store-prod.switch.tv/images/4c0a7d70-4979-4821-8c85-35e38e23862c/481495_racing.com_red_logo_16x9_rgb.png"}]},"episode_id":"/20SEC38A","broadcaster":"SEVEN"}]}},{"id":"15293a96-8cf0-4abf-b32c-0263108de691","broadcaster_code":"SEVEN","channel_id":"RACING.COM","channel_name":"RACING.COM","duration":"05:00","dvb_triplet":"1013:0502:0528","end":"2020-05-27T07:00:00+00:00","lcn":78,"start":"2020-05-27T02:00:00+00:00","tags":["captioned"],"updated_at":"2020-05-26T07:29:40+00:00","title":"Racing Live: Sale/Strathalbyn"},{"id":"d3cb2cab-ef7c-42fd-85b3-cf8643ceb014","broadcaster_code":"SEVEN","channel_id":"RACING.COM","channel_name":"RACING.COM","duration":"01:00","dvb_triplet":"1013:0502:0528","end":"2020-05-27T08:00:00+00:00","lcn":78,"episode_id":"c6b9fc0c-898c-4352-a5e7-15cff499cc10","start":"2020-05-27T07:00:00+00:00","tags":["captioned"],"updated_at":"2020-05-18T21:37:43+00:00","title":"Sectional Stars","related":{"episodes":[{"id":"c6b9fc0c-898c-4352-a5e7-15cff499cc10","updated_at":"2020-05-17T21:37:03+00:00","draft":false,"on_air":true,"synopsis":"Brent Zerafa and Nic Ashman delve deep into races and find Sectional Stars from the feature meetings. Hidden gems with horses running on and the good oil on future favourites - everything to put into your black book. (2016)","title":"Sectional Stars","categories":["channel_id/RACING.COM","genres/Sport","subgenres/Horse Racing","classification/NC","content_type/series"],"related":{"images":[{"id":"4c0a7d70-4979-4821-8c85-35e38e23862c","url":"http://img-store-prod.switch.tv/images/4c0a7d70-4979-4821-8c85-35e38e23862c/481495_racing.com_red_logo_16x9_rgb.png"}]},"episode_id":"/20SEC38A","broadcaster":"SEVEN"}]}},{"id":"1624273d-3ec4-4cee-8ead-be3b66c7ba85","broadcaster_code":"SEVEN","channel_id":"RACING.COM","channel_name":"RACING.COM","duration":"00:30","dvb_triplet":"1013:0502:0528","end":"2020-05-27T08:30:00+00:00","lcn":78,"start":"2020-05-27T08:00:00+00:00","tags":["captioned"],"updated_at":"2020-05-18T21:38:28+00:00","title":"Raceday Review - Sale"},{"id":"a790bb94-be8a-43fd-9d92-f2c78b380f9a","broadcaster_code":"SEVEN","channel_id":"RACING.COM","channel_name":"RACING.COM","duration":"01:00","dvb_triplet":"1013:0502:0528","end":"2020-05-27T09:30:00+00:00","lcn":78,"episode_id":"15f42feb-98a0-445a-9e45-3086909cd04f","start":"2020-05-27T08:30:00+00:00","tags":["captioned"],"updated_at":"2020-05-18T21:38:11+00:00","title":"After the Last","related":{"episodes":[{"id":"15f42feb-98a0-445a-9e45-3086909cd04f","updated_at":"2020-05-18T21:38:11+00:00","draft":false,"on_air":true,"synopsis":"After The Last is a news, opinion and form preview program, covering all angles of the racing industry. (2016)","title":"After the Last","categories":["channel_id/RACING.COM","genres/Sport","subgenres/Horse Racing","classification/NC","content_type/series"],"related":{"images":[{"id":"4c0a7d70-4979-4821-8c85-35e38e23862c","url":"http://img-store-prod.switch.tv/images/4c0a7d70-4979-4821-8c85-35e38e23862c/481495_racing.com_red_logo_16x9_rgb.png"}]},"episode_id":"/ATL2705A","broadcaster":"SEVEN"}]}},{"id":"ec0eb8ef-f6a2-4283-a4dd-2415a94a1b14","broadcaster_code":"SEVEN","channel_id":"RACING.COM","channel_name":"RACING.COM","duration":"01:00","dvb_triplet":"1013:0502:0528","end":"2020-05-27T10:30:00+00:00","lcn":78,"episode_id":"e981d928-1aac-43d4-8386-e4d13cb32596","start":"2020-05-27T09:30:00+00:00","tags":["captioned"],"updated_at":"2020-05-24T05:27:08+00:00","title":"Classic Racedays","related":{"episodes":[{"id":"e981d928-1aac-43d4-8386-e4d13cb32596","updated_at":"2020-05-24T05:26:42+00:00","draft":false,"on_air":true,"synopsis":"2010 Cox Plate. Re-live all the great moments from a 'Classic Raceday', all the races from the day in full, with comments from trainer and jockeys. (2020)","title":"Classic Racedays","categories":["channel_id/RACING.COM","genres/Sport","subgenres/Horse Racing","classification/NC","content_type/series"],"related":{"images":[{"id":"4c0a7d70-4979-4821-8c85-35e38e23862c","url":"http://img-store-prod.switch.tv/images/4c0a7d70-4979-4821-8c85-35e38e23862c/481495_racing.com_red_logo_16x9_rgb.png"}]},"episode_id":"/20CLS03A","broadcaster":"SEVEN"}]}},{"id":"1d271562-bf17-4e82-bd84-fa36ba8f12b1","broadcaster_code":"SEVEN","channel_id":"RACING.COM","channel_name":"RACING.COM","duration":"04:30","dvb_triplet":"1013:0502:0528","end":"2020-05-27T15:00:00+00:00","lcn":78,"episode_id":"162d6c59-e77e-41e9-9dfd-b3e9ee38119d","start":"2020-05-27T10:30:00+00:00","tags":["captioned"],"updated_at":"2020-05-25T08:30:43+00:00","title":"Racenight Live: Sha Tin","related":{"episodes":[{"id":"162d6c59-e77e-41e9-9dfd-b3e9ee38119d","updated_at":"2020-05-18T21:38:04+00:00","draft":false,"on_air":true,"synopsis":"Hong Kong thoroughbred racing from Sha Tin. (2016)","title":"Racenight Live: Sha Tin","categories":["channel_id/RACING.COM","genres/Sport","subgenres/Horse Racing","classification/NC","content_type/series"],"related":{"images":[{"id":"4c0a7d70-4979-4821-8c85-35e38e23862c","url":"http://img-store-prod.switch.tv/images/4c0a7d70-4979-4821-8c85-35e38e23862c/481495_racing.com_red_logo_16x9_rgb.png"}]},"episode_id":"/RNIT2705","broadcaster":"SEVEN"}]}}]