[{"id":"4e074e20-f152-4552-9c0f-3235bbae71b5","broadcaster_code":"TEN","channel_id":"TEN","channel_name":"TEN","duration":"01:17","dvb_triplet":"1014:0603:0635","end":"2020-05-26T10:48:00+00:00","lcn":10,"start":"2020-05-26T09:31:00+00:00","tags":["captioned","catch_up"],"updated_at":"2020-05-26T03:40:28+00:00","title":"MasterChef Australia"},{"id":"63439b48-1ccb-4b67-b7ff-54803bad224f","broadcaster_code":"TEN","channel_id":"TEN","channel_name":"TEN","duration":"00:28","dvb_triplet":"1014:0603:0635","end":"2020-05-26T11:16:00+00:00","lcn":10,"episode_id":"669da501-b7f8-4f71-ab9d-8d85b1e0245a","start":"2020-05-26T10:48:00+00:00","tags":["captioned","catch_up"],"updated_at":"2020-05-26T03:41:22+00:00","title":"How to Stay Married","related":{"episodes":[{"id":"669da501-b7f8-4f71-ab9d-8d85b1e0245a","updated_at":"2020-05-17T21:45:51+00:00","draft":false,"on_air":true,"episode_number":"4","synopsis":"When Em's pompous father and stepmother come over for a family barbecue, Greg attempts to ask them for money while Em stokes the fires of familial conflict to generate material for her book.","title":"How to Stay Married","categories":["channel_id/TEN","genres/Entertainment","classification/M","content_type/series","season_number/2"],"related":{"images":[{"id":"6ee45dad-fb3f-44b4-aab1-32147d967cf7","url":"http://img-store-prod.switch.tv/images/6ee45dad-fb3f-44b4-aab1-32147d967cf7/656164_ten_primary_1440x1080.png"}]},"episode_id":"/62736E1592730","broadcaster":"TEN"}]}},{"id":"d07d4c7d-0910-41c2-878f-4133168d0b94","broadcaster_code":"TEN","channel_id":"TEN","channel_name":"TEN","duration":"00:57","dvb_triplet":"1014:0603:0635","end":"2020-05-26T12:13:00+00:00","lcn":10,"episode_id":"2d808b7b-a693-464b-93ad-fdaec8906c16","start":"2020-05-26T11:16:00+00:00","tags":["captioned"],"updated_at":"2020-05-26T03:40:18+00:00","title":"Third Wheel","related":{"episodes":[{"id":"2d808b7b-a693-464b-93ad-fdaec8906c16","updated_at":"2019-10-26T11:53:48+00:00","draft":false,"on_air":true,"episode_number":"4","synopsis":"Gibbs' holiday at his remote cabin is interrupted by a surprise visit from friends and a call from NCIS about a robber hiding in the woods nearby.","title":"Third Wheel","categories":["channel_id/TEN","genres/Drama","classification/M","content_type/series","season_number/16"],"related":{"images":[{"id":"45cea5df-d5e7-4b8a-853d-516bf36404ba","url":"http://img-store-prod.switch.tv/images/45cea5df-d5e7-4b8a-853d-516bf36404ba/1642391_SERIES_60926.jpg"}]},"episode_id":"/60926E1546358","broadcaster":"TEN"}]}},{"id":"ea968756-ac8e-492e-81b9-dbb038d63722","broadcaster_code":"TEN","channel_id":"TEN","channel_name":"TEN","duration":"00:55","dvb_triplet":"1014:0603:0635","end":"2020-05-26T13:08:00+00:00","lcn":10,"episode_id":"7d2acdea-a087-4346-9081-2e344f7c266a","start":"2020-05-26T12:13:00+00:00","tags":["captioned","catch_up"],"updated_at":"2020-05-26T03:42:07+00:00","title":"Watch Over Me","related":{"episodes":[{"id":"7d2acdea-a087-4346-9081-2e344f7c266a","updated_at":"2020-05-17T21:45:07+00:00","draft":false,"on_air":true,"episode_number":"17","synopsis":"When an FBI agent is killed while trying to track the location of an undercover agent, NCIS must find the missing agent before the criminals find him.","title":"Watch Over Me","categories":["channel_id/TEN","genres/Drama","classification/M","content_type/series","season_number/11"],"related":{"images":[{"id":"6ee45dad-fb3f-44b4-aab1-32147d967cf7","url":"http://img-store-prod.switch.tv/images/6ee45dad-fb3f-44b4-aab1-32147d967cf7/656164_ten_primary_1440x1080.png"}]},"episode_id":"/62737E1592757","broadcaster":"TEN"}]}},{"id":"2802f4f3-d0a5-4672-92c2-615a2e969f86","broadcaster_code":"TEN","channel_id":"TEN","channel_name":"TEN","duration":"01:05","dvb_triplet":"1014:0603:0635","end":"2020-05-26T14:13:00+00:00","lcn":10,"episode_id":"cb91734c-56e4-49ed-8f29-ec819b9dc77a","start":"2020-05-26T13:08:00+00:00","tags":["captioned"],"updated_at":"2020-05-26T03:42:54+00:00","title":"The Project","related":{"episodes":[{"id":"cb91734c-56e4-49ed-8f29-ec819b9dc77a","updated_at":"2020-05-22T09:29:17+00:00","draft":false,"on_air":true,"episode_number":"222","synopsis":"Join Waleed Aly, Carrie Bickmore, Peter Helliar and Fitzy, plus guests Hannah Gadsby and David McCormack as they dissect and digest the daily news, events and hottest topics.","title":"The Project","categories":["channel_id/TEN","genres/News & Current Affairs","classification/NC","content_type/series","season_number/11"],"related":{"images":[{"id":"7a4121f3-d200-4c02-81b9-349c27304f15","url":"http://img-store-prod.switch.tv/images/7a4121f3-d200-4c02-81b9-349c27304f15/1669679_SERIES_62156.jpg"}]},"episode_id":"/62156E1582410","broadcaster":"TEN"}]}},{"id":"df149dd8-7f52-4708-ba86-25a4bb7cdd3c","broadcaster_code":"TEN","channel_id":"TEN","channel_name":"TEN","duration":"00:47","dvb_triplet":"1014:0603:0635","end":"2020-05-26T15:00:00+00:00","lcn":10,"episode_id":"48b568d9-0e9d-45c9-afdc-6e281866553a","start":"2020-05-26T14:13:00+00:00","tags":["captioned"],"updated_at":"2020-05-26T03:43:05+00:00","title":"The Late Show With Stephen Colbert","related":{"episodes":[{"id":"48b568d9-0e9d-45c9-afdc-6e281866553a","updated_at":"2020-05-21T06:28:22+00:00","draft":false,"on_air":true,"episode_number":"190","synopsis":"Stephen Colbert welcomes guests Dr Jon LaPook and Cate Blanchett.","title":"The Late Show With Stephen Colbert","categories":["channel_id/TEN","genres/Lifestyle","classification/PG","content_type/series","season_number/5"],"related":{"images":[{"id":"6ee45dad-fb3f-44b4-aab1-32147d967cf7","url":"http://img-store-prod.switch.tv/images/6ee45dad-fb3f-44b4-aab1-32147d967cf7/656164_ten_primary_1440x1080.png"}]},"episode_id":"/62376E1586107","broadcaster":"TEN"}]}},{"id":"33b0065c-8e6e-4f00-a709-a4702421e68b","broadcaster_code":"TEN","channel_id":"TEN","channel_name":"TEN","duration":"00:30","dvb_triplet":"1014:0603:0635","end":"2020-05-26T15:30:00+00:00","lcn":10,"episode_id":"94702f14-4f31-4eb4-8893-963c1eb5ec34","start":"2020-05-26T15:00:00+00:00","updated_at":"2020-05-21T06:30:41+00:00","title":"Home Shopping","related":{"episodes":[{"id":"94702f14-4f31-4eb4-8893-963c1eb5ec34","updated_at":"2020-05-23T21:42:32+00:00","draft":false,"on_air":true,"episode_number":"94","title":"Home Shopping","categories":["channel_id/TEN","genres/Lifestyle","classification/NC","content_type/series","season_number/2019","channel_id/10 Peach","channel_id/10 Bold"],"related":{"images":[{"id":"f9c2d560-3a73-4270-8e62-d629ecddcf6d","url":"http://img-store-prod.switch.tv/images/f9c2d560-3a73-4270-8e62-d629ecddcf6d/656164_ten_primary_1440x1080.png"},{"id":"4f947b11-669f-46f6-a758-f4398c2ed2d8","url":"http://img-store-prod.switch.tv/images/4f947b11-669f-46f6-a758-f4398c2ed2d8/656208_ten_peach_1440x1080.png"},{"id":"7af51f40-379e-4151-bcfb-ae10c71817c8","url":"http://img-store-prod.switch.tv/images/7af51f40-379e-4151-bcfb-ae10c71817c8/660252_10bold_1440x1080_freeviewplus.png"}]},"episode_id":"/61001E1550320","broadcaster":"TEN"}]}},{"id":"30211ee2-b4a9-4a93-a0ba-c4e84c86af14","broadcaster_code":"TEN","channel_id":"TEN","channel_name":"TEN","duration":"00:30","dvb_triplet":"1014:0603:0635","end":"2020-05-26T16:00:00+00:00","lcn":10,"episode_id":"f505919d-6294-4700-9581-03ab81955b52","start":"2020-05-26T15:30:00+00:00","updated_at":"2020-05-18T21:45:59+00:00","title":"Home Shopping","related":{"episodes":[{"id":"f505919d-6294-4700-9581-03ab81955b52","updated_at":"2020-05-17T21:45:25+00:00","draft":false,"on_air":true,"episode_number":"35","title":"Home Shopping","categories":["channel_id/10 Peach","genres/Lifestyle","classification/NC","content_type/series","season_number/2019","channel_id/TEN","channel_id/10 Bold"],"related":{"images":[{"id":"cdfb8def-2337-4bc7-af07-d8c377dd6e82","url":"http://img-store-prod.switch.tv/images/cdfb8def-2337-4bc7-af07-d8c377dd6e82/660252_10bold_1440x1080_freeviewplus.png"},{"id":"4f947b11-669f-46f6-a758-f4398c2ed2d8","url":"http://img-store-prod.switch.tv/images/4f947b11-669f-46f6-a758-f4398c2ed2d8/656208_ten_peach_1440x1080.png"},{"id":"6ee45dad-fb3f-44b4-aab1-32147d967cf7","url":"http://img-store-prod.switch.tv/images/6ee45dad-fb3f-44b4-aab1-32147d967cf7/656164_ten_primary_1440x1080.png"}]},"episode_id":"/61001E1550261","broadcaster":"TEN"}]}},{"id":"7593d555-7a41-47fa-ba5b-fc1f9e336f1b","broadcaster_code":"TEN","channel_id":"TEN","channel_name":"TEN","duration":"00:30","dvb_triplet":"1014:0603:0635","end":"2020-05-26T16:30:00+00:00","lcn":10,"episode_id":"d5834d4f-1b78-47eb-aa45-c0b38f47bb42","start":"2020-05-26T16:00:00+00:00","updated_at":"2020-05-18T21:49:20+00:00","title":"Home Shopping","related":{"episodes":[{"id":"d5834d4f-1b78-47eb-aa45-c0b38f47bb42","updated_at":"2020-05-17T21:45:00+00:00","draft":false,"on_air":true,"episode_number":"36","title":"Home Shopping","categories":["channel_id/TEN","genres/Lifestyle","classification/NC","content_type/series","season_number/2019","channel_id/10 Peach","channel_id/10 Bold"],"related":{"images":[{"id":"a2ec87fe-b23b-4308-ba9e-fa675dd47122","url":"http://img-store-prod.switch.tv/images/a2ec87fe-b23b-4308-ba9e-fa675dd47122/660252_10bold_1440x1080_freeviewplus.png"},{"id":"4f947b11-669f-46f6-a758-f4398c2ed2d8","url":"http://img-store-prod.switch.tv/images/4f947b11-669f-46f6-a758-f4398c2ed2d8/656208_ten_peach_1440x1080.png"},{"id":"6ee45dad-fb3f-44b4-aab1-32147d967cf7","url":"http://img-store-prod.switch.tv/images/6ee45dad-fb3f-44b4-aab1-32147d967cf7/656164_ten_primary_1440x1080.png"}]},"episode_id":"/61001E1550262","broadcaster":"TEN"}]}},{"id":"735fb1fa-898d-491b-a021-b50c13cf9d23","broadcaster_code":"TEN","channel_id":"TEN","channel_name":"TEN","duration":"00:30","dvb_triplet":"1014:0603:0635","end":"2020-05-26T17:00:00+00:00","lcn":10,"episode_id":"9c41086d-8b88-4e44-b5b5-2166263bf8b3","start":"2020-05-26T16:30:00+00:00","updated_at":"2020-05-18T21:46:12+00:00","title":"Home Shopping","related":{"episodes":[{"id":"9c41086d-8b88-4e44-b5b5-2166263bf8b3","updated_at":"2020-05-18T21:45:26+00:00","draft":false,"on_air":true,"episode_number":"147","title":"Home Shopping","categories":["channel_id/TEN","genres/Lifestyle","classification/NC","content_type/series","season_number/2019","channel_id/10 Peach","channel_id/10 Bold"],"related":{"images":[{"id":"0a941e53-f9cd-481f-ae1a-a05500a74028","url":"http://img-store-prod.switch.tv/images/0a941e53-f9cd-481f-ae1a-a05500a74028/656164_ten_primary_1440x1080.png"},{"id":"4f947b11-669f-46f6-a758-f4398c2ed2d8","url":"http://img-store-prod.switch.tv/images/4f947b11-669f-46f6-a758-f4398c2ed2d8/656208_ten_peach_1440x1080.png"}]},"episode_id":"/61001E1550373","broadcaster":"TEN"}]}},{"id":"6f1b3222-95b8-4061-981f-0460e75f484f","broadcaster_code":"TEN","channel_id":"TEN","channel_name":"TEN","duration":"00:30","dvb_triplet":"1014:0603:0635","end":"2020-05-26T17:30:00+00:00","lcn":10,"episode_id":"9c41086d-8b88-4e44-b5b5-2166263bf8b3","start":"2020-05-26T17:00:00+00:00","updated_at":"2020-05-18T21:46:12+00:00","title":"Home Shopping","related":{"episodes":[{"id":"9c41086d-8b88-4e44-b5b5-2166263bf8b3","updated_at":"2020-05-18T21:45:26+00:00","draft":false,"on_air":true,"episode_number":"147","title":"Home Shopping","categories":["channel_id/TEN","genres/Lifestyle","classification/NC","content_type/series","season_number/2019","channel_id/10 Peach","channel_id/10 Bold"],"related":{"images":[{"id":"0a941e53-f9cd-481f-ae1a-a05500a74028","url":"http://img-store-prod.switch.tv/images/0a941e53-f9cd-481f-ae1a-a05500a74028/656164_ten_primary_1440x1080.png"},{"id":"4f947b11-669f-46f6-a758-f4398c2ed2d8","url":"http://img-store-prod.switch.tv/images/4f947b11-669f-46f6-a758-f4398c2ed2d8/656208_ten_peach_1440x1080.png"}]},"episode_id":"/61001E1550373","broadcaster":"TEN"}]}},{"id":"54fe8fa0-1a12-4722-be3d-38bcf841672b","broadcaster_code":"TEN","channel_id":"TEN","channel_name":"TEN","duration":"00:30","dvb_triplet":"1014:0603:0635","end":"2020-05-26T18:00:00+00:00","lcn":10,"episode_id":"9c41086d-8b88-4e44-b5b5-2166263bf8b3","start":"2020-05-26T17:30:00+00:00","updated_at":"2020-05-18T21:47:07+00:00","title":"Home Shopping","related":{"episodes":[{"id":"9c41086d-8b88-4e44-b5b5-2166263bf8b3","updated_at":"2020-05-18T21:45:26+00:00","draft":false,"on_air":true,"episode_number":"147","title":"Home Shopping","categories":["channel_id/TEN","genres/Lifestyle","classification/NC","content_type/series","season_number/2019","channel_id/10 Peach","channel_id/10 Bold"],"related":{"images":[{"id":"0a941e53-f9cd-481f-ae1a-a05500a74028","url":"http://img-store-prod.switch.tv/images/0a941e53-f9cd-481f-ae1a-a05500a74028/656164_ten_primary_1440x1080.png"},{"id":"4f947b11-669f-46f6-a758-f4398c2ed2d8","url":"http://img-store-prod.switch.tv/images/4f947b11-669f-46f6-a758-f4398c2ed2d8/656208_ten_peach_1440x1080.png"}]},"episode_id":"/61001E1550373","broadcaster":"TEN"}]}},{"id":"fed03c84-3474-4162-adcd-f9c4fdbdd730","broadcaster_code":"TEN","channel_id":"TEN","channel_name":"TEN","duration":"00:30","dvb_triplet":"1014:0603:0635","end":"2020-05-26T18:30:00+00:00","lcn":10,"episode_id":"9c41086d-8b88-4e44-b5b5-2166263bf8b3","start":"2020-05-26T18:00:00+00:00","updated_at":"2020-05-18T21:47:01+00:00","title":"Home Shopping","related":{"episodes":[{"id":"9c41086d-8b88-4e44-b5b5-2166263bf8b3","updated_at":"2020-05-18T21:45:26+00:00","draft":false,"on_air":true,"episode_number":"147","title":"Home Shopping","categories":["channel_id/TEN","genres/Lifestyle","classification/NC","content_type/series","season_number/2019","channel_id/10 Peach","channel_id/10 Bold"],"related":{"images":[{"id":"0a941e53-f9cd-481f-ae1a-a05500a74028","url":"http://img-store-prod.switch.tv/images/0a941e53-f9cd-481f-ae1a-a05500a74028/656164_ten_primary_1440x1080.png"},{"id":"4f947b11-669f-46f6-a758-f4398c2ed2d8","url":"http://img-store-prod.switch.tv/images/4f947b11-669f-46f6-a758-f4398c2ed2d8/656208_ten_peach_1440x1080.png"}]},"episode_id":"/61001E1550373","broadcaster":"TEN"}]}},{"id":"2490de8d-e956-4f71-9c0a-d8e1b8dc40f3","broadcaster_code":"TEN","channel_id":"TEN","channel_name":"TEN","duration":"00:37","dvb_triplet":"1014:0603:0635","end":"2020-05-26T19:07:00+00:00","lcn":10,"episode_id":"0ba36d00-5d25-4c34-aad8-995273193eeb","start":"2020-05-26T18:30:00+00:00","updated_at":"2020-05-26T07:41:21+00:00","title":"Home Shopping","related":{"episodes":[{"id":"0ba36d00-5d25-4c34-aad8-995273193eeb","updated_at":"2020-01-26T20:40:06+00:00","draft":false,"on_air":true,"episode_number":"12","title":"Home Shopping","categories":["channel_id/TEN","genres/Lifestyle","classification/NC","content_type/series","season_number/2019","channel_id/10 Peach","channel_id/10 Bold"],"related":{"images":[{"id":"067d5b17-a4b2-44aa-ad05-cee23648ce60","url":"http://img-store-prod.switch.tv/images/067d5b17-a4b2-44aa-ad05-cee23648ce60/656164_ten_primary_1440x1080.png"},{"id":"4f947b11-669f-46f6-a758-f4398c2ed2d8","url":"http://img-store-prod.switch.tv/images/4f947b11-669f-46f6-a758-f4398c2ed2d8/656208_ten_peach_1440x1080.png"}]},"episode_id":"/61001E1550238","broadcaster":"TEN"}]}},{"id":"c94d36eb-e761-45e8-885d-f76f7036bba1","broadcaster_code":"TEN","channel_id":"TEN","channel_name":"TEN","duration":"00:53","dvb_triplet":"1014:0603:0635","end":"2020-05-26T20:00:00+00:00","lcn":10,"episode_id":"a2ac23be-2089-4372-abef-917afc28cd5d","start":"2020-05-26T19:07:00+00:00","tags":["captioned"],"updated_at":"2020-05-26T07:41:17+00:00","title":"The Talk","related":{"episodes":[{"id":"a2ac23be-2089-4372-abef-917afc28cd5d","updated_at":"2020-05-26T05:28:46+00:00","draft":false,"on_air":true,"episode_number":"173","synopsis":"Join hosts Sharon Osbourne, Sheryl Underwood, Carrie Ann Inaba, Marie Osmond, and Eve as they discuss current events, pop culture, and trending topics of the day.","title":"The Talk","categories":["channel_id/TEN","genres/Lifestyle","classification/PG","content_type/series","season_number/10"],"related":{"images":[{"id":"6ee45dad-fb3f-44b4-aab1-32147d967cf7","url":"http://img-store-prod.switch.tv/images/6ee45dad-fb3f-44b4-aab1-32147d967cf7/656164_ten_primary_1440x1080.png"}]},"episode_id":"/62296E1585111","broadcaster":"TEN"}]}},{"id":"4b2ce6a2-45b6-47db-b03b-1739b3bd47d6","broadcaster_code":"TEN","channel_id":"TEN","channel_name":"TEN","duration":"00:30","dvb_triplet":"1014:0603:0635","end":"2020-05-26T20:30:00+00:00","lcn":10,"episode_id":"dd4f6aac-08dc-4e34-a57c-01e09be2c3b1","start":"2020-05-26T20:00:00+00:00","tags":["captioned"],"updated_at":"2020-05-18T21:46:26+00:00","title":"Entertainment Tonight","related":{"episodes":[{"id":"dd4f6aac-08dc-4e34-a57c-01e09be2c3b1","updated_at":"2020-05-17T21:44:31+00:00","draft":false,"on_air":true,"episode_number":"187","synopsis":"Kevin Frazier bring us the latest celebrity news events, exclusive interviews, and behind-the-scenes first looks.","title":"Entertainment Tonight","categories":["channel_id/TEN","genres/News & Current Affairs","classification/NC","content_type/series","season_number/39"],"related":{"images":[{"id":"d3cc934e-68ba-42dc-b710-0b95b15c235f","url":"http://img-store-prod.switch.tv/images/d3cc934e-68ba-42dc-b710-0b95b15c235f/1678498_SERIES_62396.jpg"}]},"episode_id":"/62396E1586722","broadcaster":"TEN"}]}},{"id":"5af900e7-0cb8-43c2-9366-96fca459dd16","broadcaster_code":"TEN","channel_id":"TEN","channel_name":"TEN","duration":"01:30","dvb_triplet":"1014:0603:0635","end":"2020-05-26T22:00:00+00:00","lcn":10,"episode_id":"5477f9d2-a18a-4119-a375-b105fa6fbb4f","start":"2020-05-26T20:30:00+00:00","tags":["captioned"],"updated_at":"2020-05-18T21:46:07+00:00","title":"CBS This Morning","related":{"episodes":[{"id":"5477f9d2-a18a-4119-a375-b105fa6fbb4f","updated_at":"2020-05-18T21:44:51+00:00","draft":false,"on_air":true,"episode_number":"105","synopsis":"This program covers breaking news, politics, health, money, lifestyle, and pop culture.","title":"CBS This Morning","categories":["channel_id/TEN","genres/News & Current Affairs","classification/NC","content_type/series","season_number/2020"],"related":{"images":[{"id":"6ee45dad-fb3f-44b4-aab1-32147d967cf7","url":"http://img-store-prod.switch.tv/images/6ee45dad-fb3f-44b4-aab1-32147d967cf7/656164_ten_primary_1440x1080.png"}]},"episode_id":"/63036E1597392","broadcaster":"TEN"}]}},{"id":"2cfd76d2-c001-4624-bc2c-1ad402d4c068","broadcaster_code":"TEN","channel_id":"TEN","channel_name":"TEN","duration":"04:00","dvb_triplet":"1014:0603:0635","end":"2020-05-27T02:00:00+00:00","lcn":10,"episode_id":"2afb0a39-3b80-474d-9d25-7aaddf937541","start":"2020-05-26T22:00:00+00:00","tags":["captioned"],"updated_at":"2020-05-18T21:45:31+00:00","title":"Studio 10","related":{"episodes":[{"id":"2afb0a39-3b80-474d-9d25-7aaddf937541","updated_at":"2020-05-18T21:45:31+00:00","draft":false,"on_air":true,"episode_number":"103","synopsis":"Start your day off right with Sarah Harris, Kerri-Anne Kennerley, Joe Hildebrand, Angela Bishop, Denise Drysdale, and Narelda Jacobs.","title":"Studio 10","categories":["channel_id/TEN","genres/Lifestyle","classification/PG","content_type/series","season_number/2020"],"related":{"images":[{"id":"6ee45dad-fb3f-44b4-aab1-32147d967cf7","url":"http://img-store-prod.switch.tv/images/6ee45dad-fb3f-44b4-aab1-32147d967cf7/656164_ten_primary_1440x1080.png"}]},"episode_id":"/63065E1599725","broadcaster":"TEN"}]}},{"id":"94ccc06e-d87e-4898-aebd-69d2233ff00c","broadcaster_code":"TEN","channel_id":"TEN","channel_name":"TEN","duration":"01:00","dvb_triplet":"1014:0603:0635","end":"2020-05-27T03:00:00+00:00","lcn":10,"episode_id":"af4e8e78-2259-442e-8465-518e97785097","start":"2020-05-27T02:00:00+00:00","tags":["captioned"],"updated_at":"2020-05-21T22:48:08+00:00","title":"The Secrets She Keeps","related":{"episodes":[{"id":"af4e8e78-2259-442e-8465-518e97785097","updated_at":"2020-05-21T22:47:57+00:00","draft":false,"on_air":true,"episode_number":"5","synopsis":"At a vigil for baby Ben, Meghan and Agatha come face-to-face. Agatha panics over baby Rory's deteriorating health.","title":"The Secrets She Keeps","categories":["channel_id/TEN","genres/Drama","classification/M","content_type/series","season_number/1"],"related":{"images":[{"id":"6ee45dad-fb3f-44b4-aab1-32147d967cf7","url":"http://img-store-prod.switch.tv/images/6ee45dad-fb3f-44b4-aab1-32147d967cf7/656164_ten_primary_1440x1080.png"}]},"episode_id":"/61656E1572171","broadcaster":"TEN"}]}},{"id":"0035d5f6-1dbf-4d09-bdac-ab020872ae18","broadcaster_code":"TEN","channel_id":"TEN","channel_name":"TEN","duration":"01:15","dvb_triplet":"1014:0603:0635","end":"2020-05-27T04:15:00+00:00","lcn":10,"episode_id":"78398754-dcfb-46e0-9e5f-fe77554b2ced","start":"2020-05-27T03:00:00+00:00","tags":["captioned"],"updated_at":"2020-05-26T03:42:00+00:00","title":"MasterChef Australia","related":{"episodes":[{"id":"78398754-dcfb-46e0-9e5f-fe77554b2ced","updated_at":"2020-05-26T03:40:28+00:00","draft":false,"on_air":true,"episode_number":"32","synopsis":"Queen of chocolate and guest chef Kirsten Tibballs reveals that, for the pressure test, the contestants must create her wow-factor dessert the meljito.","title":"MasterChef Australia","categories":["channel_id/TEN","genres/Entertainment","subgenres/Elimination/Gameshow","classification/G","content_type/series","season_number/12"],"related":{"images":[{"id":"fc2db20e-6432-41f7-ad49-7b8f2b0508c0","url":"http://img-store-prod.switch.tv/images/fc2db20e-6432-41f7-ad49-7b8f2b0508c0/1709599_SERIES_62536.jpg","tags":["source:epg-ingestion"]}]},"episode_id":"/62536E1590116","broadcaster":"TEN"}]}},{"id":"0cc148fd-3731-462e-9cc9-90b403fd852d","broadcaster_code":"TEN","channel_id":"TEN","channel_name":"TEN","duration":"00:15","dvb_triplet":"1014:0603:0635","end":"2020-05-27T04:30:00+00:00","lcn":10,"episode_id":"d23135cc-56e7-4ac7-b0e6-036815599817","start":"2020-05-27T04:15:00+00:00","tags":["captioned"],"updated_at":"2020-05-21T06:30:49+00:00","title":"Entertainment Tonight","related":{"episodes":[{"id":"d23135cc-56e7-4ac7-b0e6-036815599817","updated_at":"2020-05-18T21:45:53+00:00","draft":false,"on_air":true,"episode_number":"188","synopsis":"Kevin Frazier bring us the latest celebrity news events, exclusive interviews, and behind-the-scenes first looks.","title":"Entertainment Tonight","categories":["channel_id/TEN","genres/News & Current Affairs","classification/NC","content_type/series","season_number/39"],"related":{"images":[{"id":"d3cc934e-68ba-42dc-b710-0b95b15c235f","url":"http://img-store-prod.switch.tv/images/d3cc934e-68ba-42dc-b710-0b95b15c235f/1678498_SERIES_62396.jpg"}]},"episode_id":"/62396E1586723","broadcaster":"TEN"}]}},{"id":"a0d2c255-e40b-42ee-9586-ddbf6fd8a443","broadcaster_code":"TEN","channel_id":"TEN","channel_name":"TEN","duration":"00:30","dvb_triplet":"1014:0603:0635","end":"2020-05-27T05:00:00+00:00","lcn":10,"episode_id":"e38004e3-276d-440b-b8b4-7db36f259cf6","start":"2020-05-27T04:30:00+00:00","tags":["captioned"],"updated_at":"2020-05-18T21:46:10+00:00","title":"Judge Judy","related":{"episodes":[{"id":"e38004e3-276d-440b-b8b4-7db36f259cf6","updated_at":"2020-03-17T20:47:03+00:00","draft":false,"on_air":true,"episode_number":"104","synopsis":"Welcome to the court room of Judge Judith Sheindlin. The cases are real, the people are real, and the rulings are final.","title":"Judge Judy","categories":["channel_id/TEN","genres/Entertainment","subgenres/Fly-on-the-Wall","classification/PG","content_type/series","season_number/23"],"related":{"images":[{"id":"6ee45dad-fb3f-44b4-aab1-32147d967cf7","url":"http://img-store-prod.switch.tv/images/6ee45dad-fb3f-44b4-aab1-32147d967cf7/656164_ten_primary_1440x1080.png"}]},"episode_id":"/61376E1546920","broadcaster":"TEN"}]}},{"id":"81cf755d-2cea-40ec-9bab-0e62b2d3da76","broadcaster_code":"TEN","channel_id":"TEN","channel_name":"TEN","duration":"00:30","dvb_triplet":"1014:0603:0635","end":"2020-05-27T05:30:00+00:00","lcn":10,"episode_id":"fedcaca6-83f1-46a4-90ac-d38f7f8fcdbc","start":"2020-05-27T05:00:00+00:00","tags":["captioned"],"updated_at":"2020-05-18T21:47:35+00:00","title":"Judge Judy","related":{"episodes":[{"id":"fedcaca6-83f1-46a4-90ac-d38f7f8fcdbc","updated_at":"2020-05-18T21:45:40+00:00","draft":false,"on_air":true,"episode_number":"251","synopsis":"Welcome to the court room of Judge Judith Sheindlin. The cases are real, the people are real, and the rulings are final.","title":"Judge Judy","categories":["channel_id/TEN","genres/Entertainment","subgenres/Fly-on-the-Wall","classification/PG","content_type/series","season_number/23"],"related":{"images":[{"id":"bd4579ae-e6f3-4353-bd55-7e5f9a072c3a","url":"http://img-store-prod.switch.tv/images/bd4579ae-e6f3-4353-bd55-7e5f9a072c3a/1667605_SERIES_60942.jpg"}]},"episode_id":"/60942E1547067","broadcaster":"TEN"}]}},{"id":"32f67798-9fd5-47ff-9d92-3831ad412f2d","broadcaster_code":"TEN","channel_id":"TEN","channel_name":"TEN","duration":"00:30","dvb_triplet":"1014:0603:0635","end":"2020-05-27T06:00:00+00:00","lcn":10,"episode_id":"f4884295-0c40-4562-acfe-dddfe21229ec","start":"2020-05-27T05:30:00+00:00","tags":["captioned"],"updated_at":"2020-05-18T21:46:30+00:00","title":"My Market Kitchen","related":{"episodes":[{"id":"f4884295-0c40-4562-acfe-dddfe21229ec","updated_at":"2020-05-18T21:46:30+00:00","draft":false,"on_air":true,"episode_number":"43","synopsis":"Celebrated chef Ben O'Donoghue sets up in one of Australia's oldest and most iconic fresh food markets, cooking amazing dishes with all of the atmosphere and drama of a working market.","title":"My Market Kitchen","categories":["channel_id/TEN","genres/Lifestyle","subgenres/Cooking/Food/Wine","classification/G","content_type/series","season_number/2020"],"related":{"images":[{"id":"6ee45dad-fb3f-44b4-aab1-32147d967cf7","url":"http://img-store-prod.switch.tv/images/6ee45dad-fb3f-44b4-aab1-32147d967cf7/656164_ten_primary_1440x1080.png"}]},"episode_id":"/63357E1609417","broadcaster":"TEN"}]}},{"id":"3c7295fa-2a5e-4150-8f95-1dcd17afc07e","broadcaster_code":"TEN","channel_id":"TEN","channel_name":"TEN","duration":"00:30","dvb_triplet":"1014:0603:0635","end":"2020-05-27T06:30:00+00:00","lcn":10,"episode_id":"731d3da7-f936-439d-8007-da4b3aaff177","start":"2020-05-27T06:00:00+00:00","tags":["captioned"],"updated_at":"2020-05-18T21:45:55+00:00","title":"Good Chef Bad Chef","related":{"episodes":[{"id":"731d3da7-f936-439d-8007-da4b3aaff177","updated_at":"2020-05-18T21:45:55+00:00","draft":false,"on_air":true,"episode_number":"48","synopsis":"Hosts Adrian Richardson and Rosie Mansfield present a cooking series showing both the healthy and indulgent ways to cook and eat.","title":"Good Chef Bad Chef","categories":["channel_id/TEN","genres/Lifestyle","classification/G","content_type/series","season_number/12"],"related":{"images":[{"id":"6ee45dad-fb3f-44b4-aab1-32147d967cf7","url":"http://img-store-prod.switch.tv/images/6ee45dad-fb3f-44b4-aab1-32147d967cf7/656164_ten_primary_1440x1080.png"}]},"episode_id":"/62358E1585737","broadcaster":"TEN"}]}},{"id":"493c1e78-c215-4060-bd71-c7819b292d5a","broadcaster_code":"TEN","channel_id":"TEN","channel_name":"TEN","duration":"00:30","dvb_triplet":"1014:0603:0635","end":"2020-05-27T07:00:00+00:00","lcn":10,"episode_id":"5fa80b8b-801d-46b5-a6d5-cd2079045519","start":"2020-05-27T06:30:00+00:00","tags":["captioned"],"updated_at":"2020-05-18T21:45:52+00:00","title":"The Bold and the Beautiful","related":{"episodes":[{"id":"5fa80b8b-801d-46b5-a6d5-cd2079045519","updated_at":"2020-05-18T21:45:52+00:00","draft":false,"on_air":true,"episode_number":"5023","synopsis":"During the flight to Australia, Ridge breathes down Rick's neck, trying to lay down the law. At arrival, Brooke lets the kids escape to the hotel while she drags Ridge along sightseeing.","title":"The Bold and the Beautiful","categories":["channel_id/TEN","genres/Drama","classification/G","content_type/series","season_number/2020"],"related":{"images":[{"id":"6ee45dad-fb3f-44b4-aab1-32147d967cf7","url":"http://img-store-prod.switch.tv/images/6ee45dad-fb3f-44b4-aab1-32147d967cf7/656164_ten_primary_1440x1080.png"}]},"episode_id":"/63659E433164","broadcaster":"TEN"}]}},{"id":"6b34918c-1417-496e-8727-afbcd2d0157e","broadcaster_code":"TEN","channel_id":"TEN","channel_name":"TEN","duration":"01:00","dvb_triplet":"1014:0603:0635","end":"2020-05-27T08:00:00+00:00","lcn":10,"episode_id":"9b6cf725-fabd-4a22-a859-c60a8cf809de","start":"2020-05-27T07:00:00+00:00","tags":["captioned","dont_miss","coming_up","catch_up"],"updated_at":"2020-05-25T05:45:51+00:00","title":"10 News First","related":{"episodes":[{"id":"9b6cf725-fabd-4a22-a859-c60a8cf809de","updated_at":"2020-05-25T05:45:23+00:00","draft":false,"on_air":true,"episode_number":"106","synopsis":"Comprehensive coverage of local, national, and international news presented by Jennifer Keyte, including sport presented by Stephen Quartermain, and the latest weather from Mike Larkan.","title":"10 News First","categories":["channel_id/TEN","genres/News & Current Affairs","classification/NC","content_type/series","season_number/2020"],"related":{"images":[{"id":"6ee45dad-fb3f-44b4-aab1-32147d967cf7","url":"http://img-store-prod.switch.tv/images/6ee45dad-fb3f-44b4-aab1-32147d967cf7/656164_ten_primary_1440x1080.png"}]},"episode_id":"/63058E1598106","broadcaster":"TEN"}]}},{"id":"a8ff4a70-ff00-410b-93bf-15b4cb65603e","broadcaster_code":"TEN","channel_id":"TEN","channel_name":"TEN","duration":"00:30","dvb_triplet":"1014:0603:0635","end":"2020-05-27T08:30:00+00:00","lcn":10,"start":"2020-05-27T08:00:00+00:00","tags":["captioned"],"updated_at":"2020-05-25T05:45:23+00:00","title":"10 News First"},{"id":"a806ff2a-a2c1-40c6-88e4-78f5bfdf2944","broadcaster_code":"TEN","channel_id":"TEN","channel_name":"TEN","duration":"01:00","dvb_triplet":"1014:0603:0635","end":"2020-05-27T09:30:00+00:00","lcn":10,"start":"2020-05-27T08:30:00+00:00","tags":["captioned","catch_up"],"updated_at":"2020-05-22T09:28:17+00:00","title":"The Project"},{"id":"e52ab5b6-d823-4db6-bb50-60ee01e10c46","broadcaster_code":"TEN","channel_id":"TEN","channel_name":"TEN","duration":"01:30","dvb_triplet":"1014:0603:0635","end":"2020-05-27T11:00:00+00:00","lcn":10,"episode_id":"c2182b01-ef69-44b5-b71f-d931ec9f485d","start":"2020-05-27T09:30:00+00:00","tags":["captioned","catch_up"],"updated_at":"2020-05-21T07:40:36+00:00","title":"MasterChef Australia","related":{"episodes":[{"id":"c2182b01-ef69-44b5-b71f-d931ec9f485d","updated_at":"2020-05-18T21:46:06+00:00","draft":false,"on_air":true,"episode_number":"33","synopsis":"The contestants lift the lids of their mystery box to find a photo sent by their loved ones. The contestants have 60 minutes to create a dish inspired by the memory in their family photo.","title":"MasterChef Australia","categories":["channel_id/TEN","genres/Entertainment","subgenres/Elimination/Gameshow","classification/NC","content_type/series","season_number/12"],"related":{"images":[{"id":"fc2db20e-6432-41f7-ad49-7b8f2b0508c0","url":"http://img-store-prod.switch.tv/images/fc2db20e-6432-41f7-ad49-7b8f2b0508c0/1709599_SERIES_62536.jpg","tags":["source:epg-ingestion"]}]},"episode_id":"/62536E1590117","broadcaster":"TEN"}]}}]