[{"id":"75dee489-6f38-49bb-ae28-4d29f163a1c9","broadcaster_code":"SBS","channel_id":"NITV","channel_name":"NITV","duration":"00:30","dvb_triplet":"3202:0300:0305","end":"2020-05-26T10:00:00+00:00","lcn":34,"start":"2020-05-26T09:30:00+00:00","updated_at":"2020-05-18T07:44:45+00:00","title":"Zombie Cops"},{"id":"ab6c4f05-bbcb-4919-9580-1fdeeb37eae9","broadcaster_code":"SBS","channel_id":"NITV","channel_name":"NITV","duration":"00:30","dvb_triplet":"3202:0300:0305","end":"2020-05-26T10:30:00+00:00","lcn":34,"episode_id":"1c21e8e2-aa74-40f2-959f-c4bb5d465575","start":"2020-05-26T10:00:00+00:00","updated_at":"2020-05-22T04:34:33+00:00","title":"Black Comedy","related":{"episodes":[{"id":"1c21e8e2-aa74-40f2-959f-c4bb5d465575","updated_at":"2020-01-11T21:17:56+00:00","draft":false,"on_air":true,"episode_number":"2","synopsis":"Meet some of the lively characters, including the Tiddas - two of the most competitive, over the top gay Blackfellas; Mavis the mean-mouthed cleaning woman; the housewives of Narromine; and Deadly Dave.","title":"Black Comedy","categories":["channel_id/NITV","genres/Entertainment","classification/M","content_type/series","season_number/1"],"related":{"images":[{"id":"6e119d4f-91c2-4bcd-b650-174939daee0f","url":"http://img-store-prod.switch.tv/images/6e119d4f-91c2-4bcd-b650-174939daee0f/1614319_P878716.jpg"}]},"episode_id":"/878716","broadcaster":"SBS"}]}},{"id":"751d8d12-c927-43f2-9089-bc7a0585a23d","broadcaster_code":"SBS","channel_id":"NITV","channel_name":"NITV","duration":"00:30","dvb_triplet":"3202:0300:0305","end":"2020-05-26T11:00:00+00:00","lcn":34,"episode_id":"01d164f5-8172-4179-a84e-eaf64ba89ad5","start":"2020-05-26T10:30:00+00:00","updated_at":"2020-05-20T05:30:31+00:00","title":"Over the Black Dot","related":{"episodes":[{"id":"01d164f5-8172-4179-a84e-eaf64ba89ad5","updated_at":"2020-05-18T21:49:36+00:00","draft":false,"on_air":true,"episode_number":"11","synopsis":"The best players from the NRL join a star-studded panel of rugby league experts to break down all the issues from the greatest game of all rugby league.","title":"Over the Black Dot","categories":["channel_id/NITV","genres/Sport","subgenres/Rugby League","classification/NC","content_type/series"],"related":{"images":[{"id":"9f8d7af1-1571-40ae-b21a-f5a9e524a687","url":"http://img-store-prod.switch.tv/images/9f8d7af1-1571-40ae-b21a-f5a9e524a687/451637_sbs_nitv_whitelogo_16x9.png"}]},"episode_id":"/1020974","broadcaster":"SBS"}]}},{"id":"748d26cb-14bc-4bd7-9fc9-033c5d37bbcf","broadcaster_code":"SBS","channel_id":"NITV","channel_name":"NITV","duration":"00:05","dvb_triplet":"3202:0300:0305","end":"2020-05-26T11:05:00+00:00","lcn":34,"episode_id":"4adbc751-f0f6-402f-b78c-12621a33918f","start":"2020-05-26T11:00:00+00:00","updated_at":"2020-05-26T00:32:01+00:00","title":"NITV News","related":{"episodes":[{"id":"4adbc751-f0f6-402f-b78c-12621a33918f","updated_at":"2020-05-26T00:31:12+00:00","draft":false,"on_air":true,"episode_number":"102","synopsis":"The latest news from the oldest living culture, we deliver Australian stories from an Indigenous perspective.","title":"NITV News","categories":["channel_id/NITV","genres/News & Current Affairs","classification/NC","content_type/series","season_number/2020"],"related":{"images":[{"id":"9f8d7af1-1571-40ae-b21a-f5a9e524a687","url":"http://img-store-prod.switch.tv/images/9f8d7af1-1571-40ae-b21a-f5a9e524a687/451637_sbs_nitv_whitelogo_16x9.png"}]},"episode_id":"/1012934","broadcaster":"SBS"}]}},{"id":"e24d2f23-f444-49e5-a795-15a15ee78e3a","broadcaster_code":"SBS","channel_id":"NITV","channel_name":"NITV","duration":"00:35","dvb_triplet":"3202:0300:0305","end":"2020-05-26T11:40:00+00:00","lcn":34,"episode_id":"4ad10edc-89f4-4237-87d7-6db01b33dfdd","start":"2020-05-26T11:05:00+00:00","tags":["blackout"],"updated_at":"2020-05-22T04:34:33+00:00","title":"North Of The Border","related":{"episodes":[{"id":"4ad10edc-89f4-4237-87d7-6db01b33dfdd","updated_at":"2020-01-21T20:41:32+00:00","draft":false,"on_air":true,"episode_number":"9","synopsis":"The boys devise a plan after hearing Paper Boi might be making another appearance.","title":"North Of The Border","categories":["channel_id/NITV","genres/Entertainment","classification/M","content_type/series","season_number/2","channel_id/SBS"],"related":{"images":[{"id":"20ea8902-dfc1-4eb4-8319-e73026ec08f3","url":"http://img-store-prod.switch.tv/images/20ea8902-dfc1-4eb4-8319-e73026ec08f3/451637_sbs_nitv_whitelogo_16x9.png"}]},"episode_id":"/932913","broadcaster":"SBS"}]}},{"id":"436b7739-fe66-4336-8cec-ff31ab8c2f71","broadcaster_code":"SBS","channel_id":"NITV","channel_name":"NITV","duration":"00:30","dvb_triplet":"3202:0300:0305","end":"2020-05-26T12:10:00+00:00","lcn":34,"start":"2020-05-26T11:40:00+00:00","updated_at":"2020-05-22T04:33:34+00:00","title":"New Zealand"},{"id":"90dff014-eb9f-4a5a-912a-12e944cc9006","broadcaster_code":"SBS","channel_id":"NITV","channel_name":"NITV","duration":"00:30","dvb_triplet":"3202:0300:0305","end":"2020-05-26T12:40:00+00:00","lcn":34,"episode_id":"46b80b59-1856-4502-87cc-cefc7ccb45ff","start":"2020-05-26T12:10:00+00:00","updated_at":"2020-05-22T08:41:34+00:00","title":"Te Teko/Murupara","related":{"episodes":[{"id":"46b80b59-1856-4502-87cc-cefc7ccb45ff","updated_at":"2019-10-28T22:49:49+00:00","draft":false,"on_air":true,"episode_number":"19","synopsis":"Matua joins Ian Tarei from Kiwi Protections Services on the job in Te Teko, then he heads to Murupara for a hunt with local hunting veteran Charlie White who is 82 and still hunting.","title":"Te Teko/Murupara","categories":["channel_id/NITV","genres/Documentary & Factual","classification/M","content_type/series","season_number/10"],"related":{"images":[{"id":"f0f637b0-2e42-4ae8-88e1-75843f6b5c6f","url":"http://img-store-prod.switch.tv/images/f0f637b0-2e42-4ae8-88e1-75843f6b5c6f/451637_sbs_nitv_whitelogo_16x9.png"},{"id":"9dad1e63-2ca4-4209-8468-719e141b1f3f","url":"http://img-store-prod.switch.tv/images/9dad1e63-2ca4-4209-8468-719e141b1f3f/1714484_P911907.jpg","tags":["source:epg-ingestion"]}]},"episode_id":"/911907","broadcaster":"SBS"}]}},{"id":"e147e2b1-505b-4148-9f65-f3bdcff17260","broadcaster_code":"SBS","channel_id":"NITV","channel_name":"NITV","duration":"00:30","dvb_triplet":"3202:0300:0305","end":"2020-05-26T13:10:00+00:00","lcn":34,"episode_id":"372588bb-cf7f-4e01-b72e-645b8ae0e487","start":"2020-05-26T12:40:00+00:00","updated_at":"2020-05-22T08:40:30+00:00","title":"Premium Meats","related":{"episodes":[{"id":"372588bb-cf7f-4e01-b72e-645b8ae0e487","updated_at":"2019-11-05T05:19:27+00:00","draft":false,"on_air":true,"episode_number":"20","synopsis":"The Hunting Aotearoa waka heads to one of the sunniest towns in Aotearoa, Blenheim, to tee up with Premium Game Meat co-owner Alan Spencer to find out more about the game meat industry.","title":"Premium Meats","categories":["channel_id/NITV","genres/Documentary & Factual","classification/M","content_type/series","season_number/10"],"related":{"images":[{"id":"39498179-8344-432d-870a-e20a7b52fca7","url":"http://img-store-prod.switch.tv/images/39498179-8344-432d-870a-e20a7b52fca7/451637_sbs_nitv_whitelogo_16x9.png"},{"id":"42680bcf-9abb-4755-9f03-88f347e122d5","url":"http://img-store-prod.switch.tv/images/42680bcf-9abb-4755-9f03-88f347e122d5/1714485_P911908.jpg","tags":["source:epg-ingestion"]}]},"episode_id":"/911908","broadcaster":"SBS"}]}},{"id":"ec1bfd2b-f9f0-4326-94e0-a860e2cc96cf","broadcaster_code":"SBS","channel_id":"NITV","channel_name":"NITV","duration":"00:30","dvb_triplet":"3202:0300:0305","end":"2020-05-26T13:40:00+00:00","lcn":34,"episode_id":"28af5029-6ac4-4766-b99c-5ab7db38b19d","start":"2020-05-26T13:10:00+00:00","updated_at":"2020-05-22T04:34:22+00:00","title":"Tangata Manu","related":{"episodes":[{"id":"28af5029-6ac4-4766-b99c-5ab7db38b19d","updated_at":"2019-11-18T04:44:38+00:00","draft":false,"on_air":true,"episode_number":"7","synopsis":"It's the grand finale. Taking part in Tangata manu, our last four warriors scale the wall to collect their eggs then master obstacles in order to become the ultimate warrior.","title":"Tangata Manu","categories":["channel_id/NITV","genres/Entertainment","classification/G","content_type/series","season_number/1"],"related":{"images":[{"id":"d6a353ab-3841-4ce4-a447-9c5fff046a2d","url":"http://img-store-prod.switch.tv/images/d6a353ab-3841-4ce4-a447-9c5fff046a2d/1691426_P966366.jpg"}]},"episode_id":"/966366","broadcaster":"SBS"}]}},{"id":"6c312e7b-1820-4deb-b9ec-fa2128b77f60","broadcaster_code":"SBS","channel_id":"NITV","channel_name":"NITV","duration":"00:30","dvb_triplet":"3202:0300:0305","end":"2020-05-26T14:10:00+00:00","lcn":34,"episode_id":"2c53bfd3-7563-4d39-81f2-a3f4e9ece03e","start":"2020-05-26T13:40:00+00:00","updated_at":"2020-05-22T04:33:45+00:00","title":"Over the Black Dot","related":{"episodes":[{"id":"2c53bfd3-7563-4d39-81f2-a3f4e9ece03e","updated_at":"2020-05-19T21:47:58+00:00","draft":false,"on_air":true,"episode_number":"11","synopsis":"The best players from the NRL join a star-studded panel of rugby league experts to break down all the issues from the greatest game of all rugby league.","title":"Over the Black Dot","categories":["channel_id/SBS","genres/Sport","subgenres/Rugby League","classification/NC","content_type/series","channel_id/NITV"],"related":{"images":[{"id":"9f8d7af1-1571-40ae-b21a-f5a9e524a687","url":"http://img-store-prod.switch.tv/images/9f8d7af1-1571-40ae-b21a-f5a9e524a687/451637_sbs_nitv_whitelogo_16x9.png"}]},"episode_id":"/1021004","broadcaster":"SBS"}]}},{"id":"130929aa-777e-4bc0-8a55-8019a767a4a3","broadcaster_code":"SBS","channel_id":"NITV","channel_name":"NITV","duration":"00:55","dvb_triplet":"3202:0300:0305","end":"2020-05-26T15:05:00+00:00","lcn":34,"episode_id":"358fd266-5f60-4736-87c8-8e2286029f32","start":"2020-05-26T14:10:00+00:00","updated_at":"2020-05-22T21:46:08+00:00","title":"Volumz","related":{"episodes":[{"id":"358fd266-5f60-4736-87c8-8e2286029f32","updated_at":"2019-11-06T01:23:56+00:00","draft":false,"on_air":true,"episode_number":"9","synopsis":"Hosted by music guru Alec Doomadgee, we feature some of our best Indigenous musicians and go behind the scenes to have a 'dorris' and get the lowdown with your favourite artists from Oz and abroad.","title":"Volumz","categories":["channel_id/NITV","genres/Arts & Culture","classification/PG","content_type/series","season_number/2"],"related":{"images":[{"id":"1a440cdc-f05e-4dfe-a6ea-cb1c9d7c82ef","url":"http://img-store-prod.switch.tv/images/1a440cdc-f05e-4dfe-a6ea-cb1c9d7c82ef/451637_sbs_nitv_whitelogo_16x9.png"}]},"episode_id":"/677894","broadcaster":"SBS"}]}},{"id":"824f27dc-1416-41bb-95a4-9e6fcd97f76f","broadcaster_code":"SBS","channel_id":"NITV","channel_name":"NITV","duration":"00:55","dvb_triplet":"3202:0300:0305","end":"2020-05-26T16:00:00+00:00","lcn":34,"episode_id":"71b16cbe-e8d6-4fe8-bf83-d99fad09c1a9","start":"2020-05-26T15:05:00+00:00","updated_at":"2020-05-22T21:46:04+00:00","title":"Volumz","related":{"episodes":[{"id":"71b16cbe-e8d6-4fe8-bf83-d99fad09c1a9","updated_at":"2019-11-06T00:53:31+00:00","draft":false,"on_air":true,"episode_number":"9","synopsis":"Hosted by music guru Alec Doomadgee, we feature some of our best Indigenous musicians and go behind the scenes to have a 'dorris' and get the lowdown with your favourite artists from Oz and abroad.","title":"Volumz","categories":["channel_id/NITV","genres/Arts & Culture","classification/PG","content_type/series","season_number/2"],"related":{"images":[{"id":"a7253529-338e-4999-90fa-84a0bf72720e","url":"http://img-store-prod.switch.tv/images/a7253529-338e-4999-90fa-84a0bf72720e/1645280_P677895.jpg"}]},"episode_id":"/677895","broadcaster":"SBS"}]}},{"id":"f6fb3a1d-b9a9-41dc-ba3b-f3463bc8704f","broadcaster_code":"SBS","channel_id":"NITV","channel_name":"NITV","duration":"01:00","dvb_triplet":"3202:0300:0305","end":"2020-05-26T17:00:00+00:00","lcn":34,"episode_id":"edbb3ea2-8520-42ee-9c3c-0876c7b27044","start":"2020-05-26T16:00:00+00:00","updated_at":"2020-05-22T21:46:57+00:00","title":"Volumz","related":{"episodes":[{"id":"edbb3ea2-8520-42ee-9c3c-0876c7b27044","updated_at":"2019-11-06T00:56:50+00:00","draft":false,"on_air":true,"episode_number":"9","synopsis":"Hosted by music guru Alec Doomadgee, we feature some of our best Indigenous musicians and go behind the scenes to have a 'dorris' and get the lowdown with your favourite artists from Oz and abroad.","title":"Volumz","categories":["channel_id/NITV","genres/Arts & Culture","classification/PG","content_type/series","season_number/2"],"related":{"images":[{"id":"348a1c63-86a2-4e0e-b296-80d8e6a194a4","url":"http://img-store-prod.switch.tv/images/348a1c63-86a2-4e0e-b296-80d8e6a194a4/1629586_P677908.jpg"}]},"episode_id":"/677908","broadcaster":"SBS"}]}},{"id":"66a71e99-ff0b-4c56-8ea1-4b74541da025","broadcaster_code":"SBS","channel_id":"NITV","channel_name":"NITV","duration":"01:00","dvb_triplet":"3202:0300:0305","end":"2020-05-26T18:00:00+00:00","lcn":34,"episode_id":"78d402a3-4098-400d-b5f1-308328dc1a86","start":"2020-05-26T17:00:00+00:00","updated_at":"2020-05-22T21:47:08+00:00","title":"Volumz","related":{"episodes":[{"id":"78d402a3-4098-400d-b5f1-308328dc1a86","updated_at":"2019-11-06T00:52:45+00:00","draft":false,"on_air":true,"episode_number":"9","synopsis":"Hosted by music guru Alec Doomadgee, we feature some of our best Indigenous musicians and go behind the scenes to have a 'dorris' and get the lowdown with your favourite artists from Oz and abroad.","title":"Volumz","categories":["channel_id/NITV","genres/Arts & Culture","classification/PG","content_type/series","season_number/2"],"related":{"images":[{"id":"33645a0e-7224-4323-84df-fec1bd267350","url":"http://img-store-prod.switch.tv/images/33645a0e-7224-4323-84df-fec1bd267350/1611592_P677909.jpg"}]},"episode_id":"/677909","broadcaster":"SBS"}]}},{"id":"12f5146d-f67e-4f6e-b6cc-da995b99b238","broadcaster_code":"SBS","channel_id":"NITV","channel_name":"NITV","duration":"01:00","dvb_triplet":"3202:0300:0305","end":"2020-05-26T19:00:00+00:00","lcn":34,"episode_id":"c4eb8ecf-bd52-40b9-8eae-82216e258536","start":"2020-05-26T18:00:00+00:00","updated_at":"2020-05-22T21:46:52+00:00","title":"Volumz","related":{"episodes":[{"id":"c4eb8ecf-bd52-40b9-8eae-82216e258536","updated_at":"2019-11-06T00:58:20+00:00","draft":false,"on_air":true,"episode_number":"9","synopsis":"Hosted by music guru Alec Doomadgee, we feature some of our best Indigenous musicians and go behind the scenes to have a 'dorris' and get the lowdown with your favourite artists from Oz and abroad.","title":"Volumz","categories":["channel_id/NITV","genres/Arts & Culture","classification/PG","content_type/series","season_number/2"],"related":{"images":[{"id":"8c396b1a-5956-473c-a1d3-b6e66ad3a6c8","url":"http://img-store-prod.switch.tv/images/8c396b1a-5956-473c-a1d3-b6e66ad3a6c8/451637_sbs_nitv_whitelogo_16x9.png"}]},"episode_id":"/677911","broadcaster":"SBS"}]}},{"id":"dbf157f0-e266-4b2e-9d05-3b3dccfcb08b","broadcaster_code":"SBS","channel_id":"NITV","channel_name":"NITV","duration":"01:00","dvb_triplet":"3202:0300:0305","end":"2020-05-26T20:00:00+00:00","lcn":34,"episode_id":"30cadf0f-dd9d-46c7-a52e-2a57fc00f281","start":"2020-05-26T19:00:00+00:00","updated_at":"2020-05-25T05:46:54+00:00","title":"Volumz","related":{"episodes":[{"id":"30cadf0f-dd9d-46c7-a52e-2a57fc00f281","updated_at":"2019-11-30T21:32:37+00:00","draft":false,"on_air":true,"episode_number":"18","synopsis":"Hosted by Alec Doomadgee, Volumz brings you music and interviews highlighting the best of the Australian Indigenous music scene.","title":"Volumz","categories":["channel_id/NITV","genres/Arts & Culture","classification/PG","content_type/series","season_number/3"],"related":{"images":[{"id":"369d5f44-d0a9-4e03-875b-3a42d9a1e179","url":"http://img-store-prod.switch.tv/images/369d5f44-d0a9-4e03-875b-3a42d9a1e179/676631_P648830.jpg"}]},"episode_id":"/648830","broadcaster":"SBS"}]}},{"id":"52f94cb2-656a-4e94-970b-0419b7f10c16","broadcaster_code":"SBS","channel_id":"NITV","channel_name":"NITV","duration":"00:26","dvb_triplet":"3202:0300:0305","end":"2020-05-26T20:26:00+00:00","lcn":34,"start":"2020-05-26T20:00:00+00:00","updated_at":"2020-05-26T00:31:13+00:00","title":"Renmark"},{"id":"d4b88e91-4b04-4629-ad8e-898ac6c05a1f","broadcaster_code":"SBS","channel_id":"NITV","channel_name":"NITV","duration":"00:27","dvb_triplet":"3202:0300:0305","end":"2020-05-26T20:53:00+00:00","lcn":34,"episode_id":"d05a6e1d-bc16-4e49-a9c5-f5f4278dbc8d","start":"2020-05-26T20:26:00+00:00","updated_at":"2020-05-19T05:32:11+00:00","title":"Blue Zoo","related":{"episodes":[{"id":"d05a6e1d-bc16-4e49-a9c5-f5f4278dbc8d","updated_at":"2020-05-19T05:32:11+00:00","draft":false,"on_air":true,"episode_number":"9","synopsis":"Bailey's in for a treat as trainer Janine introduces him to her infamous 'Fish Prep Dance'. Tallann has some serious setbacks with his seal handling techniques.","title":"Blue Zoo","categories":["channel_id/NITV","genres/Documentary & Factual","classification/G","content_type/series","season_number/1"],"related":{"images":[{"id":"b040f325-3c29-407a-a82c-0a9ab128d6e0","url":"http://img-store-prod.switch.tv/images/b040f325-3c29-407a-a82c-0a9ab128d6e0/1694493_P875138.jpg"}]},"episode_id":"/875138","broadcaster":"SBS"}]}},{"id":"b0ff3402-2050-47ea-bb71-853db482d0e2","broadcaster_code":"SBS","channel_id":"NITV","channel_name":"NITV","duration":"00:29","dvb_triplet":"3202:0300:0305","end":"2020-05-26T21:22:00+00:00","lcn":34,"episode_id":"489ec4e9-688f-4df1-b1d8-23dafbfb2e80","start":"2020-05-26T20:53:00+00:00","updated_at":"2020-05-19T05:33:08+00:00","title":"Shaolin","related":{"episodes":[{"id":"489ec4e9-688f-4df1-b1d8-23dafbfb2e80","updated_at":"2020-02-28T03:20:24+00:00","draft":false,"on_air":true,"episode_number":"7","synopsis":"On the way to Peking, our heroes find refuge in a Shaolin temple. Mendoza, hurt during a fight, is taken care of by the Great Master. At nightfall, someone sneaks in to leave a venomous snake.","title":"Shaolin","categories":["channel_id/NITV","genres/Entertainment","classification/PG","content_type/series","season_number/2"],"related":{"images":[{"id":"f6ba6aac-123b-4510-a77e-18b2d8c53ebe","url":"http://img-store-prod.switch.tv/images/f6ba6aac-123b-4510-a77e-18b2d8c53ebe/1692452_P917680.jpg"}]},"episode_id":"/917680","broadcaster":"SBS"}]}},{"id":"60225059-43bb-447a-a465-1791b8e1c363","broadcaster_code":"SBS","channel_id":"NITV","channel_name":"NITV","duration":"00:25","dvb_triplet":"3202:0300:0305","end":"2020-05-26T21:47:00+00:00","lcn":34,"episode_id":"486615b8-70f4-4fa8-ab14-2a09543bcf32","start":"2020-05-26T21:22:00+00:00","updated_at":"2020-05-19T05:33:34+00:00","title":"Seal Dance/Snowboarding Qyah Style","related":{"episodes":[{"id":"486615b8-70f4-4fa8-ab14-2a09543bcf32","updated_at":"2020-04-27T03:34:20+00:00","draft":false,"on_air":true,"episode_number":"23","synopsis":"An approaching storm forces Molly, Grandpa Nat, and Mom to make an impromptu landing on the island of Atka; inspired by Randall's snowboarding video antics, Molly decides to make her own video.","title":"Seal Dance/Snowboarding Qyah Style","categories":["channel_id/NITV","genres/Entertainment","classification/G","content_type/series"],"related":{"images":[{"id":"9f8d7af1-1571-40ae-b21a-f5a9e524a687","url":"http://img-store-prod.switch.tv/images/9f8d7af1-1571-40ae-b21a-f5a9e524a687/451637_sbs_nitv_whitelogo_16x9.png"},{"id":"b797d907-e97f-4736-9091-ceb5d901e479","url":"http://img-store-prod.switch.tv/images/b797d907-e97f-4736-9091-ceb5d901e479/1708728_P1011196.jpg","tags":["source:epg-ingestion"]}]},"episode_id":"/1011196","broadcaster":"SBS"}]}},{"id":"92e1e108-4e61-48a0-9617-0c6c52c9f799","broadcaster_code":"SBS","channel_id":"NITV","channel_name":"NITV","duration":"00:14","dvb_triplet":"3202:0300:0305","end":"2020-05-26T22:01:00+00:00","lcn":34,"episode_id":"1f474f6c-346c-4130-aa5f-9e180af36179","start":"2020-05-26T21:47:00+00:00","updated_at":"2020-05-19T05:32:26+00:00","title":"My Animal Friends","related":{"episodes":[{"id":"1f474f6c-346c-4130-aa5f-9e180af36179","updated_at":"2019-12-13T21:10:06+00:00","draft":false,"on_air":true,"episode_number":"22","synopsis":"This series is a unique look at the early life and development of young animals, edited and narrated from the viewpoint of the animals themselves.","title":"My Animal Friends","categories":["channel_id/NITV","genres/Children's","classification/G","content_type/series","season_number/3"],"related":{"images":[{"id":"d50be69e-e2d5-4226-9b83-795f6b9fad2c","url":"http://img-store-prod.switch.tv/images/d50be69e-e2d5-4226-9b83-795f6b9fad2c/451637_sbs_nitv_whitelogo_16x9.png"}]},"episode_id":"/983138","broadcaster":"SBS"}]}},{"id":"2959680a-3676-4bb6-943a-b91d07d2571f","broadcaster_code":"SBS","channel_id":"NITV","channel_name":"NITV","duration":"00:13","dvb_triplet":"3202:0300:0305","end":"2020-05-26T22:14:00+00:00","lcn":34,"episode_id":"56018c5d-29e7-485b-b3d4-6c3bed1b8e72","start":"2020-05-26T22:01:00+00:00","updated_at":"2020-05-26T03:43:18+00:00","title":"School Sleepover (Ts Creole)","related":{"episodes":[{"id":"56018c5d-29e7-485b-b3d4-6c3bed1b8e72","updated_at":"2020-05-20T05:30:06+00:00","draft":false,"on_air":true,"episode_number":"4","synopsis":"Little J is anxious about the school sleepover, while Big Cuz smuggles in her beloved teddy.","title":"School Sleepover (Ts Creole)","categories":["channel_id/NITV","genres/Children's","classification/G","content_type/series","season_number/2"],"related":{"images":[{"id":"9f8d7af1-1571-40ae-b21a-f5a9e524a687","url":"http://img-store-prod.switch.tv/images/9f8d7af1-1571-40ae-b21a-f5a9e524a687/451637_sbs_nitv_whitelogo_16x9.png"},{"id":"881de9e4-6d5d-45b8-b45d-e7816cb519f4","url":"http://img-store-prod.switch.tv/images/881de9e4-6d5d-45b8-b45d-e7816cb519f4/1715381_P1017249.jpg","tags":["source:epg-ingestion"]}]},"episode_id":"/1017249","broadcaster":"SBS"}]}},{"id":"4761b880-d1e9-4a50-bf52-daebf6b49ab1","broadcaster_code":"SBS","channel_id":"NITV","channel_name":"NITV","duration":"00:05","dvb_triplet":"3202:0300:0305","end":"2020-05-26T22:19:00+00:00","lcn":34,"start":"2020-05-26T22:14:00+00:00","updated_at":"2020-05-26T09:35:57+00:00","title":"Let's Go!"},{"id":"0d4606cd-2157-4481-8332-0fad17d1a74a","broadcaster_code":"SBS","channel_id":"NITV","channel_name":"NITV","duration":"00:28","dvb_triplet":"3202:0300:0305","end":"2020-05-26T22:47:00+00:00","lcn":34,"episode_id":"9bd84c43-38d9-446f-8fcc-c180c47e3d9e","start":"2020-05-26T22:19:00+00:00","updated_at":"2020-05-19T05:32:51+00:00","title":"Inuk","related":{"episodes":[{"id":"9bd84c43-38d9-446f-8fcc-c180c47e3d9e","updated_at":"2020-05-19T05:32:51+00:00","draft":false,"on_air":true,"episode_number":"3","synopsis":"Inuk is a highly imaginative seven-year-old Inuit boy who lives with his family in the Arctic. Destined to become a shaman, Inuk has special magical powers.","title":"Inuk","categories":["channel_id/NITV","genres/Children's","classification/G","content_type/series","season_number/3"],"related":{"images":[{"id":"62fe5b51-a578-4c3f-a04a-aceaae00dc77","url":"http://img-store-prod.switch.tv/images/62fe5b51-a578-4c3f-a04a-aceaae00dc77/1601459_P867553.jpg"}]},"episode_id":"/867553","broadcaster":"SBS"}]}},{"id":"457ae6a4-b2b4-47e6-bbbc-80b3d6af9b99","broadcaster_code":"SBS","channel_id":"NITV","channel_name":"NITV","duration":"00:22","dvb_triplet":"3202:0300:0305","end":"2020-05-26T23:09:00+00:00","lcn":34,"start":"2020-05-26T22:47:00+00:00","updated_at":"2020-05-26T00:30:35+00:00","title":"A Time To Learn"},{"id":"48a2445a-cc50-4cc1-9926-17b8627ea60a","broadcaster_code":"SBS","channel_id":"NITV","channel_name":"NITV","duration":"00:25","dvb_triplet":"3202:0300:0305","end":"2020-05-26T23:34:00+00:00","lcn":34,"episode_id":"1e9abf8b-28ea-416f-b07a-7cbb7daf3122","start":"2020-05-26T23:09:00+00:00","updated_at":"2020-05-19T05:32:06+00:00","title":"The Dreaming","related":{"episodes":[{"id":"1e9abf8b-28ea-416f-b07a-7cbb7daf3122","updated_at":"2019-11-04T23:56:17+00:00","draft":false,"on_air":true,"episode_number":"18","synopsis":"Animated traditional stories explained by the Elders. The Dolphin, NSW, and Wanka Manapulpa Minyma, WA.","title":"The Dreaming","categories":["channel_id/NITV","genres/Arts & Culture","classification/G","content_type/series","season_number/1"],"related":{"images":[{"id":"19c49eba-df20-47b9-ac99-5872529a938d","url":"http://img-store-prod.switch.tv/images/19c49eba-df20-47b9-ac99-5872529a938d/1495824_P728109.jpg"}]},"episode_id":"/728109","broadcaster":"SBS"}]}},{"id":"fcc354e1-c095-4e9f-afb8-57802b0b7352","broadcaster_code":"SBS","channel_id":"NITV","channel_name":"NITV","duration":"00:26","dvb_triplet":"3202:0300:0305","end":"2020-05-27T00:00:00+00:00","lcn":34,"episode_id":"c4c7d37d-1267-4868-9259-b26cd31820ab","start":"2020-05-26T23:34:00+00:00","updated_at":"2020-05-19T05:32:32+00:00","title":"Kagagi: The Raven","related":{"episodes":[{"id":"c4c7d37d-1267-4868-9259-b26cd31820ab","updated_at":"2020-05-19T05:32:32+00:00","draft":false,"on_air":true,"episode_number":"9","synopsis":"Matthew is an average 16-year-old, or at least he was. He has found out that he has inherited an ancient power and responsibility, and the age-old evil known as the Windingo has returned.","title":"Kagagi: The Raven","categories":["channel_id/NITV","genres/Entertainment","classification/PG","content_type/series","season_number/1"],"related":{"images":[{"id":"7b0df16d-31d4-41f5-a708-c79f21d95516","url":"http://img-store-prod.switch.tv/images/7b0df16d-31d4-41f5-a708-c79f21d95516/1632690_P780278.jpg"}]},"episode_id":"/780278","broadcaster":"SBS"}]}},{"id":"c8826aa6-39fe-4ac5-a582-ea9bc1978b74","broadcaster_code":"SBS","channel_id":"NITV","channel_name":"NITV","duration":"00:30","dvb_triplet":"3202:0300:0305","end":"2020-05-27T00:30:00+00:00","lcn":34,"episode_id":"2c53bfd3-7563-4d39-81f2-a3f4e9ece03e","start":"2020-05-27T00:00:00+00:00","updated_at":"2020-05-20T05:30:54+00:00","title":"Over the Black Dot","related":{"episodes":[{"id":"2c53bfd3-7563-4d39-81f2-a3f4e9ece03e","updated_at":"2020-05-19T21:47:58+00:00","draft":false,"on_air":true,"episode_number":"11","synopsis":"The best players from the NRL join a star-studded panel of rugby league experts to break down all the issues from the greatest game of all rugby league.","title":"Over the Black Dot","categories":["channel_id/SBS","genres/Sport","subgenres/Rugby League","classification/NC","content_type/series","channel_id/NITV"],"related":{"images":[{"id":"9f8d7af1-1571-40ae-b21a-f5a9e524a687","url":"http://img-store-prod.switch.tv/images/9f8d7af1-1571-40ae-b21a-f5a9e524a687/451637_sbs_nitv_whitelogo_16x9.png"}]},"episode_id":"/1021004","broadcaster":"SBS"}]}},{"id":"aa26410b-7dff-4351-9d58-72952c7a197b","broadcaster_code":"SBS","channel_id":"NITV","channel_name":"NITV","duration":"00:30","dvb_triplet":"3202:0300:0305","end":"2020-05-27T01:00:00+00:00","lcn":34,"episode_id":"162766e1-6bc4-470a-9e26-d60a37bfbea7","start":"2020-05-27T00:30:00+00:00","updated_at":"2020-05-21T03:53:22+00:00","title":"Keeping the Language","related":{"episodes":[{"id":"162766e1-6bc4-470a-9e26-d60a37bfbea7","updated_at":"2020-04-09T08:33:04+00:00","draft":false,"on_air":true,"synopsis":"This documentary is built around a series of interviews with the Nyul Nyul/Jabirr Jabirr cultural bosses who describe the genocide they and their people suffered in the days of the Beagle Bay Mission.","title":"Keeping the Language","categories":["channel_id/NITV","genres/Documentary & Factual","classification/PG","content_type/series"],"related":{"images":[{"id":"9f8d7af1-1571-40ae-b21a-f5a9e524a687","url":"http://img-store-prod.switch.tv/images/9f8d7af1-1571-40ae-b21a-f5a9e524a687/451637_sbs_nitv_whitelogo_16x9.png"}]},"episode_id":"/1030027","broadcaster":"SBS"}]}},{"id":"4477c582-8748-43d3-84bd-ddc35c3a6a5e","broadcaster_code":"SBS","channel_id":"NITV","channel_name":"NITV","duration":"00:05","dvb_triplet":"3202:0300:0305","end":"2020-05-27T01:05:00+00:00","lcn":34,"episode_id":"81c353f7-dfef-4ee0-a869-4f29b152c7ca","start":"2020-05-27T01:00:00+00:00","updated_at":"2020-05-19T05:32:13+00:00","title":"To The Point","related":{"episodes":[{"id":"81c353f7-dfef-4ee0-a869-4f29b152c7ca","updated_at":"2020-05-13T21:52:09+00:00","draft":false,"on_air":true,"episode_number":"6","synopsis":"This program delivers a bite-sized look at the issues that matter most to Indigenous Australians. Join Rachael Hocking and John Paul Janke for a look at the best bits of the program.","title":"To The Point","categories":["channel_id/NITV","genres/News & Current Affairs","classification/NC","content_type/series","season_number/2020"],"related":{"images":[{"id":"9f8d7af1-1571-40ae-b21a-f5a9e524a687","url":"http://img-store-prod.switch.tv/images/9f8d7af1-1571-40ae-b21a-f5a9e524a687/451637_sbs_nitv_whitelogo_16x9.png"}]},"episode_id":"/1031109","broadcaster":"SBS"}]}},{"id":"f383d858-3f2f-45f9-80d0-fdc72bd85572","broadcaster_code":"SBS","channel_id":"NITV","channel_name":"NITV","duration":"00:45","dvb_triplet":"3202:0300:0305","end":"2020-05-27T01:50:00+00:00","lcn":34,"episode_id":"b8fd169b-f9cc-4933-9889-bf09bdfbe406","start":"2020-05-27T01:05:00+00:00","updated_at":"2020-05-19T05:33:26+00:00","title":"Gifts of the Maarga","related":{"episodes":[{"id":"b8fd169b-f9cc-4933-9889-bf09bdfbe406","updated_at":"2020-01-14T21:24:30+00:00","draft":false,"on_air":true,"synopsis":"In the Pilbara, Ngaarda families have lived on their ngurra for over 50,000 years, practising culture and law. Elders are concerned that the younger generation is losing their connection to country.","title":"Gifts of the Maarga","categories":["channel_id/NITV","genres/Documentary & Factual","classification/PG","content_type/series"],"related":{"images":[{"id":"6acfaafa-eed7-4cf5-8777-b56fcb4756cc","url":"http://img-store-prod.switch.tv/images/6acfaafa-eed7-4cf5-8777-b56fcb4756cc/1699636_P989582.jpg"}]},"episode_id":"/989582","broadcaster":"SBS"}]}},{"id":"4598271f-edc4-4da7-aed9-68e51c9eb505","broadcaster_code":"SBS","channel_id":"NITV","channel_name":"NITV","duration":"00:40","dvb_triplet":"3202:0300:0305","end":"2020-05-27T02:30:00+00:00","lcn":34,"episode_id":"1b856c8f-e737-4149-ad07-cf1cf199838d","start":"2020-05-27T01:50:00+00:00","updated_at":"2020-05-22T08:39:39+00:00","title":"Footprints On Our Land","related":{"episodes":[{"id":"1b856c8f-e737-4149-ad07-cf1cf199838d","updated_at":"2019-10-02T21:46:02+00:00","draft":false,"on_air":true,"synopsis":"From life on the missions in Yass to now, this program captures Aunty Agnes' life as a survivor of racism, a caring mother and grandmother, and a strong advocate for her community. (2016)","title":"Footprints On Our Land","categories":["channel_id/NITV","genres/Documentary & Factual","classification/PG","content_type/series"],"related":{"images":[{"id":"b091f3c7-7a83-4aed-b24e-5d1e6024e032","url":"http://img-store-prod.switch.tv/images/b091f3c7-7a83-4aed-b24e-5d1e6024e032/1624684_P910321.jpg"}]},"episode_id":"/910321","broadcaster":"SBS"}]}},{"id":"00961f00-ffce-4464-8d3c-a57ccf457341","broadcaster_code":"SBS","channel_id":"NITV","channel_name":"NITV","duration":"00:30","dvb_triplet":"3202:0300:0305","end":"2020-05-27T03:00:00+00:00","lcn":34,"start":"2020-05-27T02:30:00+00:00","updated_at":"2020-05-26T00:31:29+00:00","title":"New Zealand"},{"id":"dec58497-a335-4702-806d-9a0216f6e663","broadcaster_code":"SBS","channel_id":"NITV","channel_name":"NITV","duration":"00:30","dvb_triplet":"3202:0300:0305","end":"2020-05-27T03:30:00+00:00","lcn":34,"episode_id":"3cbf0be9-d243-466e-9a90-b8fc90a4bc86","start":"2020-05-27T03:00:00+00:00","updated_at":"2020-05-22T08:41:41+00:00","title":"Zombie Cops","related":{"episodes":[{"id":"3cbf0be9-d243-466e-9a90-b8fc90a4bc86","updated_at":"2020-05-18T07:44:45+00:00","draft":false,"on_air":true,"episode_number":"6","synopsis":"We meet Minogue and O'Leary's nemeses in the form of officers Donovan and Laupepe, who have arrested what appears to be a zombie. The zombie infects Donovan, who soon infects his partner.","title":"Zombie Cops","categories":["channel_id/NITV","genres/Entertainment","classification/M","content_type/series","season_number/1","channel_id/SBS VICELAND HD","channel_id/SBS VICELAND"],"related":{"images":[{"id":"8cd4c0f3-9648-4075-ac07-8f9e19142cad","url":"http://img-store-prod.switch.tv/images/8cd4c0f3-9648-4075-ac07-8f9e19142cad/1632715_P930683.jpg"}]},"episode_id":"/930683","broadcaster":"SBS"}]}},{"id":"36552866-c464-4542-98bf-3d2b0c642b6e","broadcaster_code":"SBS","channel_id":"NITV","channel_name":"NITV","duration":"00:30","dvb_triplet":"3202:0300:0305","end":"2020-05-27T04:00:00+00:00","lcn":34,"episode_id":"28af5029-6ac4-4766-b99c-5ab7db38b19d","start":"2020-05-27T03:30:00+00:00","updated_at":"2020-05-22T08:41:35+00:00","title":"Tangata Manu","related":{"episodes":[{"id":"28af5029-6ac4-4766-b99c-5ab7db38b19d","updated_at":"2019-11-18T04:44:38+00:00","draft":false,"on_air":true,"episode_number":"7","synopsis":"It's the grand finale. Taking part in Tangata manu, our last four warriors scale the wall to collect their eggs then master obstacles in order to become the ultimate warrior.","title":"Tangata Manu","categories":["channel_id/NITV","genres/Entertainment","classification/G","content_type/series","season_number/1"],"related":{"images":[{"id":"d6a353ab-3841-4ce4-a447-9c5fff046a2d","url":"http://img-store-prod.switch.tv/images/d6a353ab-3841-4ce4-a447-9c5fff046a2d/1691426_P966366.jpg"}]},"episode_id":"/966366","broadcaster":"SBS"}]}},{"id":"286f3ecc-e925-4091-b3eb-92faf25d1252","broadcaster_code":"SBS","channel_id":"NITV","channel_name":"NITV","duration":"01:00","dvb_triplet":"3202:0300:0305","end":"2020-05-27T05:00:00+00:00","lcn":34,"episode_id":"0d0159ef-ce39-47df-bfb7-8b69c2f4a9f3","start":"2020-05-27T04:00:00+00:00","updated_at":"2020-05-26T03:43:20+00:00","title":"Bernard Fanning","related":{"episodes":[{"id":"0d0159ef-ce39-47df-bfb7-8b69c2f4a9f3","updated_at":"2020-05-19T05:33:32+00:00","draft":false,"on_air":true,"episode_number":"3","synopsis":"A weekend of culture and music in central Australia.","title":"Bernard Fanning","categories":["channel_id/NITV","genres/Arts & Culture","classification/G","content_type/series"],"related":{"images":[{"id":"eafd34b8-1ac1-4e22-95f5-23c193a3ff2c","url":"http://img-store-prod.switch.tv/images/eafd34b8-1ac1-4e22-95f5-23c193a3ff2c/1715384_P762564.jpg","tags":["source:epg-ingestion"]}]},"episode_id":"/762564","broadcaster":"SBS"}]}},{"id":"c9231c18-c44f-467e-ba9c-fab1009e3565","broadcaster_code":"SBS","channel_id":"NITV","channel_name":"NITV","duration":"00:26","dvb_triplet":"3202:0300:0305","end":"2020-05-27T05:26:00+00:00","lcn":34,"episode_id":"187d8a13-7e27-4e33-967d-4f6b9fd4840f","start":"2020-05-27T05:00:00+00:00","updated_at":"2020-05-19T05:32:37+00:00","title":"The Forest of Statues","related":{"episodes":[{"id":"187d8a13-7e27-4e33-967d-4f6b9fd4840f","updated_at":"2020-05-19T05:32:37+00:00","draft":false,"on_air":true,"episode_number":"28","synopsis":"The original 1980s animation classic that follows a young orphan called Esteban as he searches the new world for both his father and the mysterious Cities of Gold.","title":"The Forest of Statues","categories":["channel_id/NITV","genres/Entertainment","classification/PG","content_type/series","season_number/1"],"related":{"images":[{"id":"ce1ff0aa-e29d-4f99-b249-f724f343072a","url":"http://img-store-prod.switch.tv/images/ce1ff0aa-e29d-4f99-b249-f724f343072a/1689003_P660967.jpg"}]},"episode_id":"/660967","broadcaster":"SBS"}]}},{"id":"77bfb636-58eb-4813-b0ef-3f1e9d94718e","broadcaster_code":"SBS","channel_id":"NITV","channel_name":"NITV","duration":"00:29","dvb_triplet":"3202:0300:0305","end":"2020-05-27T05:55:00+00:00","lcn":34,"episode_id":"ce914695-c59a-4f84-b9fa-c1cad5596e0d","start":"2020-05-27T05:26:00+00:00","updated_at":"2020-05-19T05:32:16+00:00","title":"Tassie Devil","related":{"episodes":[{"id":"ce914695-c59a-4f84-b9fa-c1cad5596e0d","updated_at":"2020-05-19T05:32:16+00:00","draft":false,"on_air":true,"episode_number":"1","synopsis":"Brandon takes Kayne to Tasmania for a ridiculously nail-biting mission: to track down and then kiss a Tasmanian devil.","title":"Tassie Devil","categories":["channel_id/NITV","genres/Drama","classification/G","content_type/series","season_number/1"],"related":{"images":[{"id":"14117850-086b-488f-ac04-b4e01af08c4c","url":"http://img-store-prod.switch.tv/images/14117850-086b-488f-ac04-b4e01af08c4c/1587886_P625289.jpg"}]},"episode_id":"/625289","broadcaster":"SBS"}]}},{"id":"5fc8fea1-2b18-4897-8621-896edb812ddc","broadcaster_code":"SBS","channel_id":"NITV","channel_name":"NITV","duration":"00:09","dvb_triplet":"3202:0300:0305","end":"2020-05-27T06:04:00+00:00","lcn":34,"start":"2020-05-27T05:55:00+00:00","updated_at":"2020-05-26T00:31:48+00:00","title":"Drakon"},{"id":"ef17c9f0-5f7b-44aa-b1f7-9b98506f7737","broadcaster_code":"SBS","channel_id":"NITV","channel_name":"NITV","duration":"00:28","dvb_triplet":"3202:0300:0305","end":"2020-05-27T06:32:00+00:00","lcn":34,"episode_id":"c479ecb3-ba54-4c46-9e17-90ef84e115df","start":"2020-05-27T06:04:00+00:00","updated_at":"2020-05-19T05:33:29+00:00","title":"Math","related":{"episodes":[{"id":"c479ecb3-ba54-4c46-9e17-90ef84e115df","updated_at":"2020-04-30T07:53:03+00:00","draft":false,"on_air":true,"episode_number":"11","synopsis":"Professor Shawn Desaulniers says numbers are everywhere, and can you solve a Rubik's cube?","title":"Math","categories":["channel_id/NITV","genres/Drama","classification/G","content_type/series"],"related":{"images":[{"id":"6fb99d73-7a61-4c0c-a358-0bbd2638d0f8","url":"http://img-store-prod.switch.tv/images/6fb99d73-7a61-4c0c-a358-0bbd2638d0f8/451637_sbs_nitv_whitelogo_16x9.png"}]},"episode_id":"/885914","broadcaster":"SBS"}]}},{"id":"b6108edb-0260-4bd6-b44c-020094b10c16","broadcaster_code":"SBS","channel_id":"NITV","channel_name":"NITV","duration":"00:28","dvb_triplet":"3202:0300:0305","end":"2020-05-27T07:00:00+00:00","lcn":34,"start":"2020-05-27T06:32:00+00:00","updated_at":"2020-05-26T00:32:03+00:00","title":"Warburton"},{"id":"c8233093-7334-43cb-9450-f062f3236287","broadcaster_code":"SBS","channel_id":"NITV","channel_name":"NITV","duration":"00:30","dvb_triplet":"3202:0300:0305","end":"2020-05-27T07:30:00+00:00","lcn":34,"start":"2020-05-27T07:00:00+00:00","updated_at":"2020-05-19T05:33:35+00:00","title":"Inspector Red"},{"id":"1edc8a58-ac21-46bc-b845-bf6f60414345","broadcaster_code":"SBS","channel_id":"NITV","channel_name":"NITV","duration":"00:35","dvb_triplet":"3202:0300:0305","end":"2020-05-27T08:05:00+00:00","lcn":34,"episode_id":"835b6d49-0f3c-41a5-901f-6ab3175bc016","start":"2020-05-27T07:30:00+00:00","updated_at":"2020-05-19T05:32:40+00:00","title":"Bamay","related":{"episodes":[{"id":"835b6d49-0f3c-41a5-901f-6ab3175bc016","updated_at":"2020-05-19T05:32:40+00:00","draft":false,"on_air":true,"synopsis":"From the Torres Straits to Tasmania, and everywhere in between, this is a showcase of Australia's most stunning landscapes. We pay tribute to that which gives us life: Country.","title":"Bamay","categories":["channel_id/NITV","genres/Documentary & Factual","classification/G","content_type/series"],"related":{"images":[{"id":"0426fe01-dc7f-426f-9432-42d49580459f","url":"http://img-store-prod.switch.tv/images/0426fe01-dc7f-426f-9432-42d49580459f/1699907_P1015756.jpg"}]},"episode_id":"/1015756","broadcaster":"SBS"}]}},{"id":"40b5ea14-e70a-4292-962a-731423178313","broadcaster_code":"SBS","channel_id":"NITV","channel_name":"NITV","duration":"00:25","dvb_triplet":"3202:0300:0305","end":"2020-05-27T08:30:00+00:00","lcn":34,"start":"2020-05-27T08:05:00+00:00","updated_at":"2020-05-26T00:31:53+00:00","title":"French"},{"id":"a12989d1-ae28-40e9-b54a-3e298b37101a","broadcaster_code":"SBS","channel_id":"NITV","channel_name":"NITV","duration":"00:30","dvb_triplet":"3202:0300:0305","end":"2020-05-27T09:00:00+00:00","lcn":34,"episode_id":"71d3f97d-d69c-4941-a93b-8fe427c0be9f","start":"2020-05-27T08:30:00+00:00","updated_at":"2020-05-25T05:46:24+00:00","title":"Beetroot Pasta, Beef & Bloodroot","related":{"episodes":[{"id":"71d3f97d-d69c-4941-a93b-8fe427c0be9f","updated_at":"2020-05-19T05:33:03+00:00","draft":false,"on_air":true,"episode_number":"3","synopsis":"Derek learns how to make beetroot pasta, goes cattle herding on a four-wheeler and even heads country on a real hunt in the bush for indigenous bloodroot with a father and son.","title":"Beetroot Pasta, Beef & Bloodroot","categories":["channel_id/NITV","genres/Lifestyle","subgenres/Cooking/Food/Wine","classification/G","content_type/series","season_number/1","channel_id/SBS Food"],"related":{"images":[{"id":"ae25a28c-c4b2-4499-a248-1ff93d040bc9","url":"http://img-store-prod.switch.tv/images/ae25a28c-c4b2-4499-a248-1ff93d040bc9/1605995_P865384.jpg"},{"id":"b9882f68-4a37-4904-aa32-dd28713db545","url":"http://img-store-prod.switch.tv/images/b9882f68-4a37-4904-aa32-dd28713db545/1714660_P865384.jpg","tags":["source:epg-ingestion"]}]},"episode_id":"/865384","broadcaster":"SBS"}]}},{"id":"b766877f-a75a-4f25-961a-5a5cbdca7910","broadcaster_code":"SBS","channel_id":"NITV","channel_name":"NITV","duration":"00:20","dvb_triplet":"3202:0300:0305","end":"2020-05-27T09:20:00+00:00","lcn":34,"episode_id":"53a6dde1-3831-422e-b915-631ce31eb682","start":"2020-05-27T09:00:00+00:00","updated_at":"2020-05-19T05:32:45+00:00","title":"Cooking Kastom","related":{"episodes":[{"id":"53a6dde1-3831-422e-b915-631ce31eb682","updated_at":"2020-01-28T20:40:52+00:00","draft":false,"on_air":true,"episode_number":"15","synopsis":"A grandfather faces the struggle of maintaining his Alian Kastom to hunt, cook, share and showcase cultural feastings. In an ever-changing landscape, will cooking Kastom be possible in the future?","title":"Cooking Kastom","categories":["channel_id/NITV","genres/Documentary & Factual","classification/G","content_type/series"],"related":{"images":[{"id":"584160b0-6c76-41c9-9ba1-a6c46bd2f4f0","url":"http://img-store-prod.switch.tv/images/584160b0-6c76-41c9-9ba1-a6c46bd2f4f0/1700815_P973306.jpg"}]},"episode_id":"/973306","broadcaster":"SBS"}]}},{"id":"fe19e2a4-1189-46bf-b198-fab2685ed340","broadcaster_code":"SBS","channel_id":"NITV","channel_name":"NITV","duration":"00:05","dvb_triplet":"3202:0300:0305","end":"2020-05-27T09:25:00+00:00","lcn":34,"episode_id":"d00c80e2-23e3-48b5-b47b-5bef6775105c","start":"2020-05-27T09:20:00+00:00","updated_at":"2020-05-19T05:33:28+00:00","title":"Woorabinda - Outside My Window","related":{"episodes":[{"id":"d00c80e2-23e3-48b5-b47b-5bef6775105c","updated_at":"2020-01-04T21:09:58+00:00","draft":false,"on_air":true,"episode_number":"12","synopsis":"The Young, Strong and Proud project works with young people in Aboriginal and TSI communities in Queensland, with the aim of developing a series of communication resources using music and video.","title":"Woorabinda - Outside My Window","categories":["channel_id/NITV","genres/Documentary & Factual","classification/G","content_type/series"],"related":{"images":[{"id":"b6a5cb72-04f5-4ba8-a69e-c7ba6c32f18a","url":"http://img-store-prod.switch.tv/images/b6a5cb72-04f5-4ba8-a69e-c7ba6c32f18a/1647749_P906889.jpg"}]},"episode_id":"/906889","broadcaster":"SBS"}]}},{"id":"a9d24921-66f6-44eb-bec2-9ca109d71d71","broadcaster_code":"SBS","channel_id":"NITV","channel_name":"NITV","duration":"00:05","dvb_triplet":"3202:0300:0305","end":"2020-05-27T09:30:00+00:00","lcn":34,"episode_id":"6fcc0c06-01f1-4de2-8580-a7b05e19803f","start":"2020-05-27T09:25:00+00:00","updated_at":"2020-05-26T00:31:07+00:00","title":"NITV News","related":{"episodes":[{"id":"6fcc0c06-01f1-4de2-8580-a7b05e19803f","updated_at":"2020-05-26T00:31:02+00:00","draft":false,"on_air":true,"episode_number":"103","synopsis":"The latest news from the oldest living culture, we deliver Australian stories from an Indigenous perspective.","title":"NITV News","categories":["channel_id/NITV","genres/News & Current Affairs","classification/NC","content_type/series","season_number/2020"],"related":{"images":[{"id":"9f8d7af1-1571-40ae-b21a-f5a9e524a687","url":"http://img-store-prod.switch.tv/images/9f8d7af1-1571-40ae-b21a-f5a9e524a687/451637_sbs_nitv_whitelogo_16x9.png"}]},"episode_id":"/1012935","broadcaster":"SBS"}]}},{"id":"cd37f1f1-0be3-4de7-b280-dfb373cb7df4","broadcaster_code":"SBS","channel_id":"NITV","channel_name":"NITV","duration":"00:30","dvb_triplet":"3202:0300:0305","end":"2020-05-27T10:00:00+00:00","lcn":34,"start":"2020-05-27T09:30:00+00:00","updated_at":"2020-05-26T00:31:06+00:00","title":"Murchison"},{"id":"8856fc33-5eab-41bf-bf50-1b1f1d9ac593","broadcaster_code":"SBS","channel_id":"NITV","channel_name":"NITV","duration":"00:30","dvb_triplet":"3202:0300:0305","end":"2020-05-27T10:30:00+00:00","lcn":34,"start":"2020-05-27T10:00:00+00:00","updated_at":"2020-05-22T08:41:15+00:00","title":"Yokayi Footy"}]